[
    {
        "day": "Today",
        "movies": [
            {
                "name": "The Smashing Machine",
                "link": "https://www.google.com/search?sca_esv=44ad9363d71d6b60&hl=en&gl=us&q=The+Smashing+Machine&si=AMgyJEtL6yuqx8LGDGAaloaQG1F-3HWSJLJFV8FPG1mfzVpr7pFTpX3dehRqIOn6u0JOXDVtudT-mIStenAOLOihbtG_7gPsXZDgTk1NKMJ7FZdG36NAPIqVn4eQsjyRcs4x-TVhnAdlHpHj_-JPTfANQYweFBVv9OWrDgHD72I47Zhq0A5Ywpo%3D&sa=X&ved=2ahUKEwjV5o2Z4I6QAxWOJdAFHVOuMOMQxyZ6BAhBEBM",
                "showing": [
                    {
                        "time": [
                            "12:45pm",
                            "2:45pm",
                            "3:45pm",
                            "5:45pm",
                            "6:45pm",
                            "8:45pm",
                            "9:45pm",
                            "11:00pm"
                        ],
                        "type": "Standard"
                    },
                    {
                        "time": [
                            "4:30pm",
                            "7:30pm"
                        ],
                        "type": "IMAX"
                    },
                    {
                        "time": [
                            "11:00am",
                            "10:30pm"
                        ],
                        "type": "Dolby Cinema"
                    }
                ]
            },
            {
                "name": "One Battle After Another",
                "link": "https://www.google.com/search?sca_esv=44ad9363d71d6b60&hl=en&gl=us&q=One+Battle+After+Another&si=AMgyJEtL6yuqx8LGDGAaloaQG1F-3HWSJLJFV8FPG1mfzVpr7rKpOMdeVIgxcKzR76mlk6ESRsJ2WpyruKyCNzTPgh0wgYAULmxqwwe5wPnBiNRN_SZAHFVKUki_M-0RAqSzLl_WteEKhiweIooNPhKC-YhsePM01XBtJ2W4JlByW4pnNQso6cY%3D&sa=X&ved=2ahUKEwjV5o2Z4I6QAxWOJdAFHVOuMOMQxyZ6BAhBECQ",
                "showing": [
                    {
                        "time": [
                            "11:00am",
                            "11:45am",
                            "12:45pm",
                            "3:30pm",
                            "4:30pm",
                            "7:15pm",
                            "7:45pm",
                            "9:00pm"
                        ],
                        "type": "Standard"
                    },
                    {
                        "time": [
                            "10:30pm"
                        ],
                        "type": "IMAX"
                    }
                ]
            },
            {
                "name": "Gabby's Dollhouse: The Movie",
                "link": "https://www.google.com/search?sca_esv=44ad9363d71d6b60&hl=en&gl=us&q=Gabby%27s+Dollhouse:+The+Movie&si=AMgyJEtL6yuqx8LGDGAaloaQG1F-3HWSJLJFV8FPG1mfzVpr7uhBKGbsq97cz0hk0CXuHjfR3gRcVq9-A_mGRbXqJTGop8SVgJOBnC_3CQFyHn3-k6FeJ8QLywEINlm9kECCnP7o_JI2suBrYQm4kiNeRm7pelxM1wv0ddrl87HAgGWopieneSE%3D&sa=X&ved=2ahUKEwjV5o2Z4I6QAxWOJdAFHVOuMOMQxyZ6BAhBEDE",
                "showing": [
                    {
                        "time": [
                            "11:15am",
                            "1:15pm",
                            "4:00pm",
                            "6:45pm"
                        ],
                        "type": "Standard"
                    }
                ]
            },
            {
                "name": "The Strangers \u2013 Chapter 2",
                "link": "https://www.google.com/search?sca_esv=44ad9363d71d6b60&hl=en&gl=us&q=The+Strangers+%E2%80%93+Chapter+2&si=AMgyJEtL6yuqx8LGDGAaloaQG1F-3HWSJLJFV8FPG1mfzVpr7kv0FdpXmv_GKn1En9iAGCmmHDC0zYNNgQGZZELUn4zJcHfOxjVYcszcMZzZLUOeDkL3XrblWWRSo1hJCS1LFroEUiRBhDBLTrVAc28SzVkWoK1JKMWMFOdnzKVOF3jrcFQZGSU%3D",
                "showing": [
                    {
                        "time": [
                            "11:30am",
                            "2:15pm",
                            "5:00pm",
                            "8:15pm",
                            "11:00pm"
                        ],
                        "type": "Standard"
                    }
                ]
            },
            {
                "name": "The Conjuring: Last Rites",
                "link": "https://www.google.com/search?sca_esv=44ad9363d71d6b60&hl=en&gl=us&q=The+Conjuring:+Last+Rites&si=AMgyJEtL6yuqx8LGDGAaloaQG1F-3HWSJLJFV8FPG1mfzVpr7uLtZyVurtHgm0PFWEPcAKtTNKpZUsGMh5LfkwdBHH89QcYRYl-JnQTH4cuPVJHNzX0ym21dd5V7QVBMsqcHLb4wSD9e--tqL5z4nncIKJumdGFc0-y1LvrXcxE0fYR1z9pcssM%3D",
                "showing": [
                    {
                        "time": [
                            "12:45pm",
                            "4:00pm",
                            "7:15pm",
                            "10:30pm"
                        ],
                        "type": "Standard"
                    }
                ]
            },
            {
                "name": "Demon Slayer: Kimetsu No Yaiba The Movie: Infinity Castle",
                "link": "https://www.google.com/search?sca_esv=44ad9363d71d6b60&hl=en&gl=us&q=Demon+Slayer:+Kimetsu+No+Yaiba+The+Movie:+Infinity+Castle&si=AMgyJEtL6yuqx8LGDGAaloaQG1F-3HWSJLJFV8FPG1mfzVpr7kDjG2IS--41swzef_MpaMiBczpZWaT0xadENqJHhkJJXe5ahFpuIry1kBvqsJo0lphhKiYqXD7UdFA3k16jAZstbKDbXqR6QUncn2luA8xGceSnJWTYxgYFhhuLwLggQBfVegw%3D",
                "showing": [
                    {
                        "time": [
                            "3:45pm",
                            "9:30pm"
                        ],
                        "type": "Standard"
                    },
                    {
                        "time": [
                            "12:15pm",
                            "7:15pm",
                            "10:15pm"
                        ],
                        "type": "Standard"
                    }
                ]
            },
            {
                "name": "Avatar: The Way of Water Re-Release 3D",
                "link": "https://www.google.com/search?sca_esv=44ad9363d71d6b60&hl=en&gl=us&q=Avatar:+The+Way+of+Water+Re-Release+3D&si=AMgyJEtL6yuqx8LGDGAaloaQG1F-3HWSJLJFV8FPG1mfzVpr7gmzW5qv5okuqfMDm47oXEmV0MGUWh-sxqZrUMBdVGWvSvKGEM5XtU1vs8Q9S4hmwEyLB5trIwNedUa_430ikcmE4OAuQBu_2J4OoOVBISZXgBHhPtdAp73yEn41-Rb1493GWBI%3D",
                "showing": [
                    {
                        "time": [
                            "12:00pm"
                        ],
                        "type": "IMAX 3D"
                    },
                    {
                        "time": [
                            "2:00pm",
                            "6:15pm"
                        ],
                        "type": "3D"
                    }
                ]
            },
            {
                "name": "The Long Walk",
                "link": "https://www.google.com/search?sca_esv=44ad9363d71d6b60&hl=en&gl=us&q=The+Long+Walk&si=AMgyJEtL6yuqx8LGDGAaloaQG1F-3HWSJLJFV8FPG1mfzVpr7r-4V46gmTlu4_dzI96ROD5714y21laa13MFiUoRfSXnyNTZKl6uykWCZJxWKu-yPC0Bbl_K4NXEhFe2Vd0tZhRIGmSc6ZkGLHAAVLSF25BVAcPR4NNOxqb2pY3eaZ-kD9nymiU%3D",
                "showing": [
                    {
                        "time": [
                            "4:45pm",
                            "8:00pm",
                            "10:45pm"
                        ],
                        "type": "Standard"
                    }
                ]
            },
            {
                "name": "Good Boy",
                "link": "https://www.google.com/search?sca_esv=44ad9363d71d6b60&hl=en&gl=us&q=Good+Boy&si=AMgyJEtL6yuqx8LGDGAaloaQG1F-3HWSJLJFV8FPG1mfzVpr7rt-pH93pC0MCSpAdNKloM9FIOaf6zcxL3lk2ePUkS74Jn37KgsQ0rfXLowf6yISldTRA0J5dWyN2CMzEf9Tw68e_Uc7LLtqDucoSnNaSSxmbMwN1hbTqVJyQYAjZcxbWBpXXto%3D",
                "showing": [
                    {
                        "time": [
                            "11:00am",
                            "12:45pm",
                            "3:00pm",
                            "5:15pm",
                            "7:30pm",
                            "8:30pm",
                            "9:45pm",
                            "10:45pm"
                        ],
                        "type": "Standard"
                    }
                ]
            },
            {
                "name": "Downton Abbey: The Grand Finale",
                "link": "https://www.google.com/search?sca_esv=44ad9363d71d6b60&hl=en&gl=us&q=Downton+Abbey:+The+Grand+Finale&si=AMgyJEtL6yuqx8LGDGAaloaQG1F-3HWSJLJFV8FPG1mfzVpr7hTGgaq6AP_6TkuZX5Pf2f1Xb8qBOAGvTGUEodCcYyEZbiWrNkpuU4eLGYLw8oR_OfdCFBhC5NBlww4OtqWncLJvblWJXG_QIoyjDzIq_YhxOq_z-AnA3W7un9K9uXC6mzKXbz0%3D",
                "showing": [
                    {
                        "time": [
                            "12:00pm"
                        ],
                        "type": "Standard"
                    }
                ]
            },
            {
                "name": "Him",
                "link": "https://www.google.com/search?sca_esv=44ad9363d71d6b60&hl=en&gl=us&q=Him&si=AMgyJEtL6yuqx8LGDGAaloaQG1F-3HWSJLJFV8FPG1mfzVpr7mTYznzzSMIVBbUEDLGMxKmii1W-v9nsnG-24kplPq9pwgQ-1O1FA3Ci7H2fBln5evBK9kxjh9dYerde2a3_RZkFedEQs1r4BJvksfGMDzP-sRt1rO9BBrlSx2U-QUAQIkSqecQ%3D",
                "showing": [
                    {
                        "time": [
                            "1:00pm",
                            "6:15pm"
                        ],
                        "type": "Standard"
                    }
                ]
            },
            {
                "name": "Anemone",
                "link": "https://www.google.com/search?sca_esv=44ad9363d71d6b60&hl=en&gl=us&q=Anemone&si=AMgyJEtL6yuqx8LGDGAaloaQG1F-3HWSJLJFV8FPG1mfzVpr7s2uDltDIW1XlRefV3C3PCsxmiKUj5otmLQcaaOV5SMPfN8yEBVvaAH-ViJeGWX2HY55AU39wg2eUkUTJoi10dzR3ys4FDcc4HUyeuAcdHhTUma_fbtNr4DlZrcn9ORqcNd0P-c%3D",
                "showing": [
                    {
                        "time": [
                            "1:00pm",
                            "4:00pm",
                            "7:00pm",
                            "10:00pm"
                        ],
                        "type": "Standard"
                    }
                ]
            },
            {
                "name": "Bone Lake",
                "link": "https://www.google.com/search?sca_esv=44ad9363d71d6b60&hl=en&gl=us&q=Bone+Lake&si=AMgyJEtL6yuqx8LGDGAaloaQG1F-3HWSJLJFV8FPG1mfzVpr7gBai5At1MRuG3dTPhls8E1O9mP86kEQQA_fELMJL9sGSXD7USLmrj0tzofW6tGQs6TNh5hD5qXHx4rEd9rqHxhU6GywC7k3DHFW0lvrxSEop47ljlYeEJamwqfQLpiwb-N7gKE%3D",
                "showing": [
                    {
                        "time": [
                            "12:00pm",
                            "2:30pm",
                            "5:00pm",
                            "7:30pm",
                            "10:00pm",
                            "11:00pm"
                        ],
                        "type": "Standard"
                    },
                    {
                        "time": [
                            "3:45pm"
                        ],
                        "type": "Standard"
                    }
                ]
            },
            {
                "name": "Casper: 30th Anniversary",
                "link": "https://www.google.com/search?sca_esv=44ad9363d71d6b60&hl=en&gl=us&q=Casper:+30th+Anniversary&si=AMgyJEtL6yuqx8LGDGAaloaQG1F-3HWSJLJFV8FPG1mfzVpr7szPlFI0dAAyHaLSICDt-9XKkxi0iqc4uL_MaHv8y155xN1_bQ7A5tU-2AdUnkJASaNWtJWpQwvSd5a4MyYS4-QGsgCyEe67udUdGBMauzP2_6g1fU3wKVtpErp16ubAiTP7p8I%3D",
                "showing": [
                    {
                        "time": [
                            "3:45pm",
                            "6:30pm"
                        ],
                        "type": "Standard"
                    }
                ]
            },
            {
                "name": "Kantara A Legend: Chapter 1",
                "link": "https://www.google.com/search?sca_esv=44ad9363d71d6b60&hl=en&gl=us&q=Kantara+A+Legend:+Chapter+1&si=AMgyJEtDcoZTubXsRk8TZioN0aq7DlbGMYlPSjPPUZB8zAtUmv9SYBQK4Y25uFn3GHv9mhax4CI6-8_nl_8f60o2ujmun5mAeYh_9PGGoGAhvZ2NPFAFCw_e5Hax4zmasL45GCRo_Rny9vFKLErqofDO2InXYNGwJpNg5oFZ0cqJzPB15Y5lYt-EFbnfT_f7QAI0ST3tia0G_VTzxybsezxuavYpDaugB-E0gzoYgQVpX18K8vEf7Rg%3D",
                "showing": [
                    {
                        "time": [
                            "11:30am",
                            "3:15pm",
                            "5:15pm",
                            "9:00pm"
                        ],
                        "type": "Standard"
                    }
                ]
            },
            {
                "name": "Perfect Blue Remastered",
                "link": "https://www.google.com/search?sca_esv=44ad9363d71d6b60&hl=en&gl=us&q=Perfect+Blue+Remastered&si=AMgyJEtDcoZTubXsRk8TZioN0aq7DlbGMYlPSjPPUZB8zAtUmv9SYBQK4Y25uFn3GHv9mhaGSO-rJYp8KJWuG4zNhTgupUy371O7t3NrLZXaDA7rVb8r_3DoA5m4pJZS5y7jcC71FFKvuYug9BnUOL1WWaNmDTgegcbCnYLTEGiIJI3j_IWVXclCA5nvMwFTQjPj6nOzIV0_iK0jT-9WEzRxJRLzZkmQaAhMuhtX6pGtd9X7UJukfCw%3D",
                "showing": [
                    {
                        "time": [
                            "11:00am",
                            "1:30pm",
                            "4:00pm",
                            "6:30pm",
                            "9:45pm"
                        ],
                        "type": "Standard"
                    }
                ]
            },
            {
                "name": "Eleanor the Great",
                "link": "https://www.google.com/search?sca_esv=44ad9363d71d6b60&hl=en&gl=us&q=Eleanor+the+Great&si=AMgyJEtL6yuqx8LGDGAaloaQG1F-3HWSJLJFV8FPG1mfzVpr7hBAQsFwG_ccq3aSQsof1jws5R0dca7IL2Cl8QFyfDCagrdVdF0lMh2nDwva9CMeEfdF1povGZ3L2zHB4hQsJv0ha3G70nVDFoXLM1F8Ew5cIiCgzkLqKZXkRwQ-4nDh9XZx_38%3D",
                "showing": [
                    {
                        "time": [
                            "1:00pm",
                            "9:15pm"
                        ],
                        "type": "Standard"
                    }
                ]
            },
            {
                "name": "A Big Bold Beautiful Journey",
                "link": "https://www.google.com/search?sca_esv=44ad9363d71d6b60&hl=en&gl=us&q=A+Big+Bold+Beautiful+Journey&si=AMgyJEtL6yuqx8LGDGAaloaQG1F-3HWSJLJFV8FPG1mfzVpr7lh_OJeIF5VP2j0JGt-sG18bL79zEEl1DQVn_XPAFmnV7L6Omkn-StRpJXOO69qtZpMTep-n8eom8AbD5GWT5lXDu-4vkYS7rcCFQjubjM6SAD-l8McSPWX_B47vXkWqogm6t34%3D",
                "showing": [
                    {
                        "time": [
                            "3:00pm",
                            "5:15pm"
                        ],
                        "type": "Standard"
                    }
                ]
            },
            {
                "name": "Dead of Winter",
                "link": "https://www.google.com/search?sca_esv=44ad9363d71d6b60&hl=en&gl=us&q=Dead+of+Winter&si=AMgyJEtL6yuqx8LGDGAaloaQG1F-3HWSJLJFV8FPG1mfzVpr7nqHv1tt0Zz8npbHwoHQqX68J_oCd1dJY7eXZuU9SeAPy01gVWlECANMHmVp3CyrzVHIJthjgvpGu_4Zu_bFOLshbXtpaUXlsEwWtzV7tbiyy0wnI9UBN4RI5MvujiUeoQ6c20w%3D",
                "showing": [
                    {
                        "time": [
                            "2:30pm",
                            "5:45pm"
                        ],
                        "type": "Standard"
                    }
                ]
            },
            {
                "name": "Coyotes",
                "link": "https://www.google.com/search?sca_esv=44ad9363d71d6b60&hl=en&gl=us&q=Coyotes&si=AMgyJEtDcoZTubXsRk8TZioN0aq7DlbGMYlPSjPPUZB8zAtUmv9SYBQK4Y25uFn3GHv9mhbYm-Fh2PSB6Zz_UHnFnv4XqAakhosaAvn61Mi2HagUR_oHgBRT0WO6MD4hy4lcz_-hC5cB-hI7qXxBYwR-yTfj0SLi7IzNsoMXjvbRlQAfGkO9mcBf0kGpKrMdsIbB3s0KopivFu9t7O0OUUf07Nh6dMFi1A%3D%3D",
                "showing": [
                    {
                        "time": [
                            "9:45pm"
                        ],
                        "type": "Standard"
                    }
                ]
            },
            {
                "name": "The Devil's Rejects 20th Anniversary",
                "link": "https://www.google.com/search?sca_esv=44ad9363d71d6b60&hl=en&gl=us&q=The+Devil%27s+Rejects+20th+Anniversary&si=AMgyJEtDcoZTubXsRk8TZioN0aq7DlbGMYlPSjPPUZB8zAtUmv9SYBQK4Y25uFn3GHv9mhZ4uO3A-r0BTBYxzWRunGUWcVgvOjx_X4ITaRusrwHF71Nz8ZaWsJ0G8QkBhV7rFXbwSqOEm7SkYiltOxmuvWHJowjO7v8mT1-2pmt05x-dwtX-JQM590dTg6vZZGPXOiZ089ta4-iKCkBoy-nEJcyj5VZ3mWhR1Lz6Sn2EgGbjmBpln_l-XwhKzsq9yeABEvZPgeCz",
                "showing": [
                    {
                        "time": [
                            "7:00pm"
                        ],
                        "type": "Standard"
                    }
                ]
            },
            {
                "name": "They Call Him OG",
                "link": "https://www.google.com/search?sca_esv=44ad9363d71d6b60&hl=en&gl=us&q=They+Call+Him+OG&si=AMgyJEtDcoZTubXsRk8TZioN0aq7DlbGMYlPSjPPUZB8zAtUmv9SYBQK4Y25uFn3GHv9mhaphcEOhY7AGtDO3Dd9ENfWihu-H2S4xFTGS_ydR0HVeLEcyR6oaklNGme56uwtMNjX9Pr9JNp9MzrwZTdTPyiJB-ZgCfj7PVnwLFmOZKbExjh5dj8UOL7S9YF4230DAqECw-UkhpDM1JhU_S4ZnBvAGF4cBzCi-a6zSMYapwiphvM2QJU%3D",
                "showing": [
                    {
                        "time": [
                            "11:45am",
                            "6:00pm"
                        ],
                        "type": "Standard"
                    }
                ]
            },
            {
                "name": "Sunny Sanskari Ki Tulsi Kumari",
                "link": "https://www.google.com/search?sca_esv=44ad9363d71d6b60&hl=en&gl=us&q=Sunny+Sanskari+Ki+Tulsi+Kumari&si=AMgyJEtDcoZTubXsRk8TZioN0aq7DlbGMYlPSjPPUZB8zAtUmv9SYBQK4Y25uFn3GHv9mhY0MZZLrTjqjlSarKfYDlqPDyVQvGPWIOSIz4EAiV2QDIdedbi1ZkxZAilgluI2da_H5vdfRyYYkC4bRo5tsz-AB-swYrd_NpX0Vk3VhOKuIFJQ0XbKcFGQb6JPDucHo3_OSRGzBcgzoexVZWhXAfP2WAEM53afrn86iDQRVUBYFXJF5cyX447hQYewA_rI4UcgDAo9",
                "showing": [
                    {
                        "time": [
                            "11:45am",
                            "3:15pm"
                        ],
                        "type": "Standard"
                    }
                ]
            },
            {
                "name": "Killing Faith",
                "link": "https://www.google.com/search?sca_esv=44ad9363d71d6b60&hl=en&gl=us&q=Killing+Faith&si=AMgyJEtDcoZTubXsRk8TZioN0aq7DlbGMYlPSjPPUZB8zAtUmv9SYBQK4Y25uFn3GHv9mhYHk9O5EAUArP5HNqB3_SymfdLfg_wGIL2DV131kBljEPx6vsqQ6k8vC2Bj3HX5yYK7e8zVFuZvqZxyLLRyhvq0TnQz3Rg-3IRv-udFoWzU_h6BX08HFKRNbOSu7_v3s1Uouwh9gAvxFIpoPy7XBZEMyjl3eA%3D%3D",
                "showing": [
                    {
                        "time": [
                            "1:15pm",
                            "9:45pm"
                        ],
                        "type": "Standard"
                    }
                ]
            },
            {
                "name": "Are We Good?",
                "link": "https://www.google.com/search?sca_esv=44ad9363d71d6b60&hl=en&gl=us&q=Are+We+Good%3F&si=AMgyJEtDcoZTubXsRk8TZioN0aq7DlbGMYlPSjPPUZB8zAtUmv9SYBQK4Y25uFn3GHv9mhaH7xff6szHJLRPoeJtRCCSDuV-KIx92kCCFV9z44NJHdZV4JkspZy6rTpa1ZLFYQGdzN2JDLvYp2rKjWvCnbXQ9W3gYLgKg-wG22B_REx0-ICDhFZ2Bv4MnXxds7zeaBiTluLnY7rp2iyDsTGGpa8uVi1U2A%3D%3D",
                "showing": [
                    {
                        "time": [
                            "11:00am",
                            "1:40pm",
                            "4:15pm",
                            "7:00pm"
                        ],
                        "type": "Standard"
                    }
                ]
            },
            {
                "name": "Afterburn",
                "link": "https://www.google.com/search?sca_esv=44ad9363d71d6b60&hl=en&gl=us&q=Afterburn&si=AMgyJEtDcoZTubXsRk8TZioN0aq7DlbGMYlPSjPPUZB8zAtUmv9SYBQK4Y25uFn3GHv9mhY3a9wU0JzeuGoochlCd9WtbKyAcZaoc1H4EmBKcL0p_jtccSOgVGjyDTQWwlkNmgFfabJmEDj_mxgV4cZlRTaF_N1EsfosNWgmXLA0PpjtzN_R_gH6QNQ3YLihSJgopeBGk13YjMRco5QKmUm1CdZgDZwnCA%3D%3D",
                "showing": [
                    {
                        "time": [
                            "3:15pm",
                            "10:45pm"
                        ],
                        "type": "Standard"
                    }
                ]
            },
            {
                "name": "A Writer's Odyssey 2",
                "link": "https://www.google.com/search?sca_esv=44ad9363d71d6b60&hl=en&gl=us&q=A+Writer%27s+Odyssey+2&si=AMgyJEtDcoZTubXsRk8TZioN0aq7DlbGMYlPSjPPUZB8zAtUmv9SYBQK4Y25uFn3GHv9mhbgUV4Lgtg8aV8DdvYkez4Y8YT43Arm6SdthO9YInesJTBQcyzHJweBvXLvXdoG8WwMIUTXszE9diEUCImwW8jN8GlWKoLKfnREG2TogjhJogP1RrEmgkqY7-vpKNitSBUmmxILCveNUk50HTebgJ-YgatHg7NpVs-bzfBFQ1_pt6WRXnM%3D",
                "showing": [
                    {
                        "time": [
                            "4:00pm",
                            "9:30pm"
                        ],
                        "type": "Standard"
                    }
                ]
            },
            {
                "name": "The Road Between Us: The Ultimate Rescue",
                "link": "https://www.google.com/search?sca_esv=44ad9363d71d6b60&hl=en&gl=us&q=The+Road+Between+Us:+The+Ultimate+Rescue&si=AMgyJEtDcoZTubXsRk8TZioN0aq7DlbGMYlPSjPPUZB8zAtUmv9SYBQK4Y25uFn3GHv9mhZ62iC4QzUfzdPQw3Nbmp69j_YzDP8TqaIY9yfz3fPZ0kxAllh0m9SjONu-wqKIGQIw-eQFeunrEc9_iOHpCISkslHive2S1wANskUiseYrWdzbnTN_a-bAf7Cf2qLwzVzSiTFAu66x56ufjGoYThsKr24Pc6Pf3nCTxceensFhH7aIUqLHbHRB60cbfHE-DbTf0kx8",
                "showing": [
                    {
                        "time": [
                            "11:45am",
                            "2:15pm"
                        ],
                        "type": "Standard"
                    }
                ]
            },
            {
                "name": "One Big Happy Family",
                "link": "https://www.google.com/search?sca_esv=44ad9363d71d6b60&hl=en&gl=us&q=One+Big+Happy+Family&si=AMgyJEtL6yuqx8LGDGAaloaQG1F-3HWSJLJFV8FPG1mfzVpr7vjN_XhqnI3L6X84IIs88TJ3yl97dd487AsKz8VvgQ4cRdKaWesCAQ73BrfqkvkDB2NY4qdAFhAjYSs7UP2vLJWdN603Ao___mhQqpeBnEf6aTYu5UwLttQ41FCRPZ2DPxiBe3Q%3D",
                "showing": [
                    {
                        "time": [
                            "12:00pm",
                            "7:15pm",
                            "9:00pm"
                        ],
                        "type": "Standard"
                    }
                ]
            },
            {
                "name": "Nikka Zaildar 4",
                "link": "https://www.google.com/search?sca_esv=44ad9363d71d6b60&hl=en&gl=us&q=Nikka+Zaildar+4&si=AMgyJEtDcoZTubXsRk8TZioN0aq7DlbGMYlPSjPPUZB8zAtUmv9SYBQK4Y25uFn3GHv9mhaRxrECF8I_phKRnn0syMRNSQKuyU8oFkNjbcI-QA16NEgnRKY-i-oAP-S63MWK51kq30uiPIVESnjH5yaCBKeaGLlUdijCpDusfNTGc7YPlNGTG0zVBN9D_10z2-z5873_D2LLHsTkx1SuR8eQvEo2RwRG8LePbBJGb9O2PPWCOnkLJOY%3D",
                "showing": [
                    {
                        "time": [
                            "2:00pm"
                        ],
                        "type": "Standard"
                    }
                ]
            },
            {
                "name": "Que l'Amour",
                "link": "https://www.google.com/search?sca_esv=44ad9363d71d6b60&hl=en&gl=us&q=Que+l%27Amour&si=AMgyJEtDcoZTubXsRk8TZioN0aq7DlbGMYlPSjPPUZB8zAtUmv9SYBQK4Y25uFn3GHv9mhbHJTUs4WSiQvQkfX8_80KDnmIFEd-nvLdnD2etdKPLIsSO57UDdBUCFJv3GZA8u7f09y1CEsDjUQdrBj-yRjxLRFo8DtPf6BGKVh6oHIOJQctpH2R9wgGBr1j1bycDC64vFrJ2lS-Zs-Pop4VjTTHCOkm4jA%3D%3D",
                "showing": [
                    {
                        "time": [
                            "7:30pm"
                        ],
                        "type": "Standard"
                    }
                ]
            }
        ]
    },
    {
        "day": "Tomorrow",
        "movies": [
            {
                "name": "The Smashing Machine",
                "link": "https://www.google.com/search?sca_esv=44ad9363d71d6b60&hl=en&gl=us&q=The+Smashing+Machine&si=AMgyJEtL6yuqx8LGDGAaloaQG1F-3HWSJLJFV8FPG1mfzVpr7pFTpX3dehRqIOn6u0JOXDVtudT-mIStenAOLOihbtG_7gPsXZDgTk1NKMJ7FZdG36NAPIqVn4eQsjyRcs4x-TVhnAdlHpHj_-JPTfANQYweFBVv9OWrDgHD72I47Zhq0A5Ywpo%3D",
                "showing": [
                    {
                        "time": [
                            "12:45pm",
                            "2:45pm",
                            "3:45pm",
                            "4:45pm",
                            "5:45pm",
                            "6:45pm",
                            "7:45pm",
                            "8:45pm",
                            "9:45pm",
                            "11:00pm"
                        ],
                        "type": "Standard"
                    },
                    {
                        "time": [
                            "11:00am",
                            "10:30pm"
                        ],
                        "type": "Dolby Cinema"
                    }
                ]
            },
            {
                "name": "One Battle After Another",
                "link": "https://www.google.com/search?sca_esv=44ad9363d71d6b60&hl=en&gl=us&q=One+Battle+After+Another&si=AMgyJEtL6yuqx8LGDGAaloaQG1F-3HWSJLJFV8FPG1mfzVpr7rKpOMdeVIgxcKzR76mlk6ESRsJ2WpyruKyCNzTPgh0wgYAULmxqwwe5wPnBiNRN_SZAHFVKUki_M-0RAqSzLl_WteEKhiweIooNPhKC-YhsePM01XBtJ2W4JlByW4pnNQso6cY%3D",
                "showing": [
                    {
                        "time": [
                            "11:00am",
                            "12:30pm",
                            "1:00pm",
                            "4:30pm",
                            "7:45pm",
                            "9:00pm"
                        ],
                        "type": "Standard"
                    },
                    {
                        "time": [
                            "10:30pm"
                        ],
                        "type": "IMAX"
                    }
                ]
            },
            {
                "name": "Gabby's Dollhouse: The Movie",
                "link": "https://www.google.com/search?sca_esv=44ad9363d71d6b60&hl=en&gl=us&q=Gabby%27s+Dollhouse:+The+Movie&si=AMgyJEtL6yuqx8LGDGAaloaQG1F-3HWSJLJFV8FPG1mfzVpr7uhBKGbsq97cz0hk0CXuHjfR3gRcVq9-A_mGRbXqJTGop8SVgJOBnC_3CQFyHn3-k6FeJ8QLywEINlm9kECCnP7o_JI2suBrYQm4kiNeRm7pelxM1wv0ddrl87HAgGWopieneSE%3D",
                "showing": [
                    {
                        "time": [
                            "11:15am",
                            "1:15pm",
                            "4:00pm",
                            "6:45pm"
                        ],
                        "type": "Standard"
                    }
                ]
            },
            {
                "name": "The Strangers \u2013 Chapter 2",
                "link": "https://www.google.com/search?sca_esv=44ad9363d71d6b60&hl=en&gl=us&q=The+Strangers+%E2%80%93+Chapter+2&si=AMgyJEtL6yuqx8LGDGAaloaQG1F-3HWSJLJFV8FPG1mfzVpr7kv0FdpXmv_GKn1En9iAGCmmHDC0zYNNgQGZZELUn4zJcHfOxjVYcszcMZzZLUOeDkL3XrblWWRSo1hJCS1LFroEUiRBhDBLTrVAc28SzVkWoK1JKMWMFOdnzKVOF3jrcFQZGSU%3D",
                "showing": [
                    {
                        "time": [
                            "11:30am",
                            "2:15pm",
                            "5:00pm",
                            "8:15pm",
                            "11:00pm"
                        ],
                        "type": "Standard"
                    }
                ]
            },
            {
                "name": "The Conjuring: Last Rites",
                "link": "https://www.google.com/search?sca_esv=44ad9363d71d6b60&hl=en&gl=us&q=The+Conjuring:+Last+Rites&si=AMgyJEtL6yuqx8LGDGAaloaQG1F-3HWSJLJFV8FPG1mfzVpr7uLtZyVurtHgm0PFWEPcAKtTNKpZUsGMh5LfkwdBHH89QcYRYl-JnQTH4cuPVJHNzX0ym21dd5V7QVBMsqcHLb4wSD9e--tqL5z4nncIKJumdGFc0-y1LvrXcxE0fYR1z9pcssM%3D",
                "showing": [
                    {
                        "time": [
                            "12:45pm",
                            "4:00pm",
                            "7:15pm",
                            "10:30pm"
                        ],
                        "type": "Standard"
                    }
                ]
            },
            {
                "name": "Demon Slayer: Kimetsu No Yaiba The Movie: Infinity Castle",
                "link": "https://www.google.com/search?sca_esv=44ad9363d71d6b60&hl=en&gl=us&q=Demon+Slayer:+Kimetsu+No+Yaiba+The+Movie:+Infinity+Castle&si=AMgyJEtL6yuqx8LGDGAaloaQG1F-3HWSJLJFV8FPG1mfzVpr7kDjG2IS--41swzef_MpaMiBczpZWaT0xadENqJHhkJJXe5ahFpuIry1kBvqsJo0lphhKiYqXD7UdFA3k16jAZstbKDbXqR6QUncn2luA8xGceSnJWTYxgYFhhuLwLggQBfVegw%3D",
                "showing": [
                    {
                        "time": [
                            "3:15pm",
                            "9:30pm"
                        ],
                        "type": "Standard"
                    },
                    {
                        "time": [
                            "11:45am",
                            "6:45pm",
                            "10:15pm"
                        ],
                        "type": "Standard"
                    }
                ]
            },
            {
                "name": "Avatar: The Way of Water Re-Release 3D",
                "link": "https://www.google.com/search?sca_esv=44ad9363d71d6b60&hl=en&gl=us&q=Avatar:+The+Way+of+Water+Re-Release+3D&si=AMgyJEtL6yuqx8LGDGAaloaQG1F-3HWSJLJFV8FPG1mfzVpr7gmzW5qv5okuqfMDm47oXEmV0MGUWh-sxqZrUMBdVGWvSvKGEM5XtU1vs8Q9S4hmwEyLB5trIwNedUa_430ikcmE4OAuQBu_2J4OoOVBISZXgBHhPtdAp73yEn41-Rb1493GWBI%3D",
                "showing": [
                    {
                        "time": [
                            "12:00pm"
                        ],
                        "type": "IMAX 3D"
                    },
                    {
                        "time": [
                            "2:00pm",
                            "6:15pm"
                        ],
                        "type": "3D"
                    }
                ]
            },
            {
                "name": "The Long Walk",
                "link": "https://www.google.com/search?sca_esv=44ad9363d71d6b60&hl=en&gl=us&q=The+Long+Walk&si=AMgyJEtL6yuqx8LGDGAaloaQG1F-3HWSJLJFV8FPG1mfzVpr7r-4V46gmTlu4_dzI96ROD5714y21laa13MFiUoRfSXnyNTZKl6uykWCZJxWKu-yPC0Bbl_K4NXEhFe2Vd0tZhRIGmSc6ZkGLHAAVLSF25BVAcPR4NNOxqb2pY3eaZ-kD9nymiU%3D",
                "showing": [
                    {
                        "time": [
                            "5:15pm",
                            "8:00pm",
                            "10:45pm"
                        ],
                        "type": "Standard"
                    }
                ]
            },
            {
                "name": "Good Boy",
                "link": "https://www.google.com/search?sca_esv=44ad9363d71d6b60&hl=en&gl=us&q=Good+Boy&si=AMgyJEtL6yuqx8LGDGAaloaQG1F-3HWSJLJFV8FPG1mfzVpr7rt-pH93pC0MCSpAdNKloM9FIOaf6zcxL3lk2ePUkS74Jn37KgsQ0rfXLowf6yISldTRA0J5dWyN2CMzEf9Tw68e_Uc7LLtqDucoSnNaSSxmbMwN1hbTqVJyQYAjZcxbWBpXXto%3D",
                "showing": [
                    {
                        "time": [
                            "11:00am",
                            "12:45pm",
                            "3:00pm",
                            "5:15pm",
                            "7:30pm",
                            "8:30pm",
                            "9:45pm",
                            "11:00pm"
                        ],
                        "type": "Standard"
                    }
                ]
            },
            {
                "name": "Downton Abbey: The Grand Finale",
                "link": "https://www.google.com/search?sca_esv=44ad9363d71d6b60&hl=en&gl=us&q=Downton+Abbey:+The+Grand+Finale&si=AMgyJEtL6yuqx8LGDGAaloaQG1F-3HWSJLJFV8FPG1mfzVpr7hTGgaq6AP_6TkuZX5Pf2f1Xb8qBOAGvTGUEodCcYyEZbiWrNkpuU4eLGYLw8oR_OfdCFBhC5NBlww4OtqWncLJvblWJXG_QIoyjDzIq_YhxOq_z-AnA3W7un9K9uXC6mzKXbz0%3D",
                "showing": [
                    {
                        "time": [
                            "12:00pm"
                        ],
                        "type": "Standard"
                    }
                ]
            },
            {
                "name": "Him",
                "link": "https://www.google.com/search?sca_esv=44ad9363d71d6b60&hl=en&gl=us&q=Him&si=AMgyJEtL6yuqx8LGDGAaloaQG1F-3HWSJLJFV8FPG1mfzVpr7mTYznzzSMIVBbUEDLGMxKmii1W-v9nsnG-24kplPq9pwgQ-1O1FA3Ci7H2fBln5evBK9kxjh9dYerde2a3_RZkFedEQs1r4BJvksfGMDzP-sRt1rO9BBrlSx2U-QUAQIkSqecQ%3D",
                "showing": [
                    {
                        "time": [
                            "5:00pm",
                            "7:45pm"
                        ],
                        "type": "Standard"
                    }
                ]
            },
            {
                "name": "Anemone",
                "link": "https://www.google.com/search?sca_esv=44ad9363d71d6b60&hl=en&gl=us&q=Anemone&si=AMgyJEtL6yuqx8LGDGAaloaQG1F-3HWSJLJFV8FPG1mfzVpr7s2uDltDIW1XlRefV3C3PCsxmiKUj5otmLQcaaOV5SMPfN8yEBVvaAH-ViJeGWX2HY55AU39wg2eUkUTJoi10dzR3ys4FDcc4HUyeuAcdHhTUma_fbtNr4DlZrcn9ORqcNd0P-c%3D",
                "showing": [
                    {
                        "time": [
                            "1:00pm",
                            "4:00pm",
                            "7:00pm",
                            "10:00pm"
                        ],
                        "type": "Standard"
                    }
                ]
            },
            {
                "name": "Bone Lake",
                "link": "https://www.google.com/search?sca_esv=44ad9363d71d6b60&hl=en&gl=us&q=Bone+Lake&si=AMgyJEtL6yuqx8LGDGAaloaQG1F-3HWSJLJFV8FPG1mfzVpr7gBai5At1MRuG3dTPhls8E1O9mP86kEQQA_fELMJL9sGSXD7USLmrj0tzofW6tGQs6TNh5hD5qXHx4rEd9rqHxhU6GywC7k3DHFW0lvrxSEop47ljlYeEJamwqfQLpiwb-N7gKE%3D",
                "showing": [
                    {
                        "time": [
                            "12:00pm",
                            "2:30pm",
                            "5:00pm",
                            "7:30pm",
                            "10:00pm"
                        ],
                        "type": "Standard"
                    }
                ]
            },
            {
                "name": "Casper: 30th Anniversary",
                "link": "https://www.google.com/search?sca_esv=44ad9363d71d6b60&hl=en&gl=us&q=Casper:+30th+Anniversary&si=AMgyJEtL6yuqx8LGDGAaloaQG1F-3HWSJLJFV8FPG1mfzVpr7szPlFI0dAAyHaLSICDt-9XKkxi0iqc4uL_MaHv8y155xN1_bQ7A5tU-2AdUnkJASaNWtJWpQwvSd5a4MyYS4-QGsgCyEe67udUdGBMauzP2_6g1fU3wKVtpErp16ubAiTP7p8I%3D",
                "showing": [
                    {
                        "time": [
                            "3:45pm",
                            "6:30pm"
                        ],
                        "type": "Standard"
                    }
                ]
            },
            {
                "name": "Kantara A Legend: Chapter 1",
                "link": "https://www.google.com/search?sca_esv=44ad9363d71d6b60&hl=en&gl=us&q=Kantara+A+Legend:+Chapter+1&si=AMgyJEtDcoZTubXsRk8TZioN0aq7DlbGMYlPSjPPUZB8zAtUmv9SYBQK4Y25uFn3GHv9mhax4CI6-8_nl_8f60o2ujmun5mAeYh_9PGGoGAhvZ2NPFAFCw_e5Hax4zmasL45GCRo_Rny9vFKLErqofDO2InXYNGwJpNg5oFZ0cqJzPB15Y5lYt-EFbnfT_f7QAI0ST3tia0G_VTzxybsezxuavYpDaugB-E0gzoYgQVpX18K8vEf7Rg%3D",
                "showing": [
                    {
                        "time": [
                            "3:15pm",
                            "5:15pm",
                            "9:00pm"
                        ],
                        "type": "Standard"
                    }
                ]
            },
            {
                "name": "Perfect Blue Remastered",
                "link": "https://www.google.com/search?sca_esv=44ad9363d71d6b60&hl=en&gl=us&q=Perfect+Blue+Remastered&si=AMgyJEtDcoZTubXsRk8TZioN0aq7DlbGMYlPSjPPUZB8zAtUmv9SYBQK4Y25uFn3GHv9mhaGSO-rJYp8KJWuG4zNhTgupUy371O7t3NrLZXaDA7rVb8r_3DoA5m4pJZS5y7jcC71FFKvuYug9BnUOL1WWaNmDTgegcbCnYLTEGiIJI3j_IWVXclCA5nvMwFTQjPj6nOzIV0_iK0jT-9WEzRxJRLzZkmQaAhMuhtX6pGtd9X7UJukfCw%3D",
                "showing": [
                    {
                        "time": [
                            "11:00am",
                            "1:30pm",
                            "4:00pm",
                            "6:30pm",
                            "9:00pm",
                            "10:00pm"
                        ],
                        "type": "Standard"
                    }
                ]
            },
            {
                "name": "Eleanor the Great",
                "link": "https://www.google.com/search?sca_esv=44ad9363d71d6b60&hl=en&gl=us&q=Eleanor+the+Great&si=AMgyJEtL6yuqx8LGDGAaloaQG1F-3HWSJLJFV8FPG1mfzVpr7hBAQsFwG_ccq3aSQsof1jws5R0dca7IL2Cl8QFyfDCagrdVdF0lMh2nDwva9CMeEfdF1povGZ3L2zHB4hQsJv0ha3G70nVDFoXLM1F8Ew5cIiCgzkLqKZXkRwQ-4nDh9XZx_38%3D",
                "showing": [
                    {
                        "time": [
                            "1:00pm",
                            "9:15pm"
                        ],
                        "type": "Standard"
                    }
                ]
            },
            {
                "name": "A Big Bold Beautiful Journey",
                "link": "https://www.google.com/search?sca_esv=44ad9363d71d6b60&hl=en&gl=us&q=A+Big+Bold+Beautiful+Journey&si=AMgyJEtL6yuqx8LGDGAaloaQG1F-3HWSJLJFV8FPG1mfzVpr7lh_OJeIF5VP2j0JGt-sG18bL79zEEl1DQVn_XPAFmnV7L6Omkn-StRpJXOO69qtZpMTep-n8eom8AbD5GWT5lXDu-4vkYS7rcCFQjubjM6SAD-l8McSPWX_B47vXkWqogm6t34%3D",
                "showing": [
                    {
                        "time": [
                            "3:00pm"
                        ],
                        "type": "Standard"
                    }
                ]
            },
            {
                "name": "Dead of Winter",
                "link": "https://www.google.com/search?sca_esv=44ad9363d71d6b60&hl=en&gl=us&q=Dead+of+Winter&si=AMgyJEtL6yuqx8LGDGAaloaQG1F-3HWSJLJFV8FPG1mfzVpr7nqHv1tt0Zz8npbHwoHQqX68J_oCd1dJY7eXZuU9SeAPy01gVWlECANMHmVp3CyrzVHIJthjgvpGu_4Zu_bFOLshbXtpaUXlsEwWtzV7tbiyy0wnI9UBN4RI5MvujiUeoQ6c20w%3D",
                "showing": [
                    {
                        "time": [
                            "5:45pm"
                        ],
                        "type": "Standard"
                    }
                ]
            },
            {
                "name": "Coyotes",
                "link": "https://www.google.com/search?sca_esv=44ad9363d71d6b60&hl=en&gl=us&q=Coyotes&si=AMgyJEtDcoZTubXsRk8TZioN0aq7DlbGMYlPSjPPUZB8zAtUmv9SYBQK4Y25uFn3GHv9mhbYm-Fh2PSB6Zz_UHnFnv4XqAakhosaAvn61Mi2HagUR_oHgBRT0WO6MD4hy4lcz_-hC5cB-hI7qXxBYwR-yTfj0SLi7IzNsoMXjvbRlQAfGkO9mcBf0kGpKrMdsIbB3s0KopivFu9t7O0OUUf07Nh6dMFi1A%3D%3D",
                "showing": [
                    {
                        "time": [
                            "9:45pm"
                        ],
                        "type": "Standard"
                    }
                ]
            },
            {
                "name": "They Call Him OG",
                "link": "https://www.google.com/search?sca_esv=44ad9363d71d6b60&hl=en&gl=us&q=They+Call+Him+OG&si=AMgyJEtDcoZTubXsRk8TZioN0aq7DlbGMYlPSjPPUZB8zAtUmv9SYBQK4Y25uFn3GHv9mhaphcEOhY7AGtDO3Dd9ENfWihu-H2S4xFTGS_ydR0HVeLEcyR6oaklNGme56uwtMNjX9Pr9JNp9MzrwZTdTPyiJB-ZgCfj7PVnwLFmOZKbExjh5dj8UOL7S9YF4230DAqECw-UkhpDM1JhU_S4ZnBvAGF4cBzCi-a6zSMYapwiphvM2QJU%3D",
                "showing": [
                    {
                        "time": [
                            "11:45am",
                            "6:00pm"
                        ],
                        "type": "Standard"
                    }
                ]
            },
            {
                "name": "Sunny Sanskari Ki Tulsi Kumari",
                "link": "https://www.google.com/search?sca_esv=44ad9363d71d6b60&hl=en&gl=us&q=Sunny+Sanskari+Ki+Tulsi+Kumari&si=AMgyJEtDcoZTubXsRk8TZioN0aq7DlbGMYlPSjPPUZB8zAtUmv9SYBQK4Y25uFn3GHv9mhY0MZZLrTjqjlSarKfYDlqPDyVQvGPWIOSIz4EAiV2QDIdedbi1ZkxZAilgluI2da_H5vdfRyYYkC4bRo5tsz-AB-swYrd_NpX0Vk3VhOKuIFJQ0XbKcFGQb6JPDucHo3_OSRGzBcgzoexVZWhXAfP2WAEM53afrn86iDQRVUBYFXJF5cyX447hQYewA_rI4UcgDAo9",
                "showing": [
                    {
                        "time": [
                            "11:45am",
                            "1:30pm"
                        ],
                        "type": "Standard"
                    }
                ]
            },
            {
                "name": "Killing Faith",
                "link": "https://www.google.com/search?sca_esv=44ad9363d71d6b60&hl=en&gl=us&q=Killing+Faith&si=AMgyJEtDcoZTubXsRk8TZioN0aq7DlbGMYlPSjPPUZB8zAtUmv9SYBQK4Y25uFn3GHv9mhYHk9O5EAUArP5HNqB3_SymfdLfg_wGIL2DV131kBljEPx6vsqQ6k8vC2Bj3HX5yYK7e8zVFuZvqZxyLLRyhvq0TnQz3Rg-3IRv-udFoWzU_h6BX08HFKRNbOSu7_v3s1Uouwh9gAvxFIpoPy7XBZEMyjl3eA%3D%3D",
                "showing": [
                    {
                        "time": [
                            "1:15pm",
                            "9:45pm"
                        ],
                        "type": "Standard"
                    }
                ]
            },
            {
                "name": "Are We Good?",
                "link": "https://www.google.com/search?sca_esv=44ad9363d71d6b60&hl=en&gl=us&q=Are+We+Good%3F&si=AMgyJEtDcoZTubXsRk8TZioN0aq7DlbGMYlPSjPPUZB8zAtUmv9SYBQK4Y25uFn3GHv9mhaH7xff6szHJLRPoeJtRCCSDuV-KIx92kCCFV9z44NJHdZV4JkspZy6rTpa1ZLFYQGdzN2JDLvYp2rKjWvCnbXQ9W3gYLgKg-wG22B_REx0-ICDhFZ2Bv4MnXxds7zeaBiTluLnY7rp2iyDsTGGpa8uVi1U2A%3D%3D",
                "showing": [
                    {
                        "time": [
                            "11:00am",
                            "1:40pm",
                            "4:15pm",
                            "7:00pm"
                        ],
                        "type": "Standard"
                    }
                ]
            },
            {
                "name": "Broken Mary: The Kevin Matthews Story",
                "link": "https://www.google.com/search?sca_esv=44ad9363d71d6b60&hl=en&gl=us&q=Broken+Mary:+The+Kevin+Matthews+Story&si=AMgyJEtL6yuqx8LGDGAaloaQG1F-3HWSJLJFV8FPG1mfzVpr7uhPAxUhB2PoWYMEA-Jz6nKa4ss3XeLkZxKjJ2HlSAyOokZi47QHeSbjMeH5Gv4zo07691bZX2ZWczGAWCawz5a0cocE06QewxNa58U4YZyTqX5I1ISlljQrCykHbXx0D4zFUkE%3D",
                "showing": [
                    {
                        "time": [
                            "7:00pm"
                        ],
                        "type": "Standard"
                    }
                ]
            },
            {
                "name": "Afterburn",
                "link": "https://www.google.com/search?sca_esv=44ad9363d71d6b60&hl=en&gl=us&q=Afterburn&si=AMgyJEtDcoZTubXsRk8TZioN0aq7DlbGMYlPSjPPUZB8zAtUmv9SYBQK4Y25uFn3GHv9mhY3a9wU0JzeuGoochlCd9WtbKyAcZaoc1H4EmBKcL0p_jtccSOgVGjyDTQWwlkNmgFfabJmEDj_mxgV4cZlRTaF_N1EsfosNWgmXLA0PpjtzN_R_gH6QNQ3YLihSJgopeBGk13YjMRco5QKmUm1CdZgDZwnCA%3D%3D",
                "showing": [
                    {
                        "time": [
                            "3:15pm",
                            "10:45pm"
                        ],
                        "type": "Standard"
                    }
                ]
            },
            {
                "name": "A Writer's Odyssey 2",
                "link": "https://www.google.com/search?sca_esv=44ad9363d71d6b60&hl=en&gl=us&q=A+Writer%27s+Odyssey+2&si=AMgyJEtDcoZTubXsRk8TZioN0aq7DlbGMYlPSjPPUZB8zAtUmv9SYBQK4Y25uFn3GHv9mhbgUV4Lgtg8aV8DdvYkez4Y8YT43Arm6SdthO9YInesJTBQcyzHJweBvXLvXdoG8WwMIUTXszE9diEUCImwW8jN8GlWKoLKfnREG2TogjhJogP1RrEmgkqY7-vpKNitSBUmmxILCveNUk50HTebgJ-YgatHg7NpVs-bzfBFQ1_pt6WRXnM%3D",
                "showing": [
                    {
                        "time": [
                            "4:00pm",
                            "9:15pm"
                        ],
                        "type": "Standard"
                    }
                ]
            },
            {
                "name": "The Road Between Us: The Ultimate Rescue",
                "link": "https://www.google.com/search?sca_esv=44ad9363d71d6b60&hl=en&gl=us&q=The+Road+Between+Us:+The+Ultimate+Rescue&si=AMgyJEtDcoZTubXsRk8TZioN0aq7DlbGMYlPSjPPUZB8zAtUmv9SYBQK4Y25uFn3GHv9mhZ62iC4QzUfzdPQw3Nbmp69j_YzDP8TqaIY9yfz3fPZ0kxAllh0m9SjONu-wqKIGQIw-eQFeunrEc9_iOHpCISkslHive2S1wANskUiseYrWdzbnTN_a-bAf7Cf2qLwzVzSiTFAu66x56ufjGoYThsKr24Pc6Pf3nCTxceensFhH7aIUqLHbHRB60cbfHE-DbTf0kx8",
                "showing": [
                    {
                        "time": [
                            "12:15pm",
                            "2:45pm"
                        ],
                        "type": "Standard"
                    }
                ]
            },
            {
                "name": "One Big Happy Family",
                "link": "https://www.google.com/search?sca_esv=44ad9363d71d6b60&hl=en&gl=us&q=One+Big+Happy+Family&si=AMgyJEtL6yuqx8LGDGAaloaQG1F-3HWSJLJFV8FPG1mfzVpr7vjN_XhqnI3L6X84IIs88TJ3yl97dd487AsKz8VvgQ4cRdKaWesCAQ73BrfqkvkDB2NY4qdAFhAjYSs7UP2vLJWdN603Ao___mhQqpeBnEf6aTYu5UwLttQ41FCRPZ2DPxiBe3Q%3D",
                "showing": [
                    {
                        "time": [
                            "11:00am",
                            "7:15pm",
                            "10:30pm"
                        ],
                        "type": "Standard"
                    }
                ]
            },
            {
                "name": "Nikka Zaildar 4",
                "link": "https://www.google.com/search?sca_esv=44ad9363d71d6b60&hl=en&gl=us&q=Nikka+Zaildar+4&si=AMgyJEtDcoZTubXsRk8TZioN0aq7DlbGMYlPSjPPUZB8zAtUmv9SYBQK4Y25uFn3GHv9mhaRxrECF8I_phKRnn0syMRNSQKuyU8oFkNjbcI-QA16NEgnRKY-i-oAP-S63MWK51kq30uiPIVESnjH5yaCBKeaGLlUdijCpDusfNTGc7YPlNGTG0zVBN9D_10z2-z5873_D2LLHsTkx1SuR8eQvEo2RwRG8LePbBJGb9O2PPWCOnkLJOY%3D",
                "showing": [
                    {
                        "time": [
                            "2:00pm"
                        ],
                        "type": "Standard"
                    }
                ]
            }
        ]
    },
    {
        "day": "Wed",
        "date": "Oct 8",
        "movies": [
            {
                "name": "The Smashing Machine",
                "link": "https://www.google.com/search?sca_esv=44ad9363d71d6b60&hl=en&gl=us&q=The+Smashing+Machine&si=AMgyJEtL6yuqx8LGDGAaloaQG1F-3HWSJLJFV8FPG1mfzVpr7pFTpX3dehRqIOn6u0JOXDVtudT-mIStenAOLOihbtG_7gPsXZDgTk1NKMJ7FZdG36NAPIqVn4eQsjyRcs4x-TVhnAdlHpHj_-JPTfANQYweFBVv9OWrDgHD72I47Zhq0A5Ywpo%3D",
                "showing": [
                    {
                        "time": [
                            "12:45pm",
                            "1:45pm",
                            "3:45pm",
                            "4:45pm",
                            "6:45pm",
                            "9:00pm",
                            "9:45pm",
                            "10:15pm"
                        ],
                        "type": "Standard"
                    },
                    {
                        "time": [
                            "11:45am"
                        ],
                        "type": "IMAX"
                    },
                    {
                        "time": [
                            "2:45pm"
                        ],
                        "type": "Standard"
                    },
                    {
                        "time": [
                            "11:00am",
                            "11:00pm"
                        ],
                        "type": "Dolby Cinema"
                    }
                ]
            },
            {
                "name": "One Battle After Another",
                "link": "https://www.google.com/search?sca_esv=44ad9363d71d6b60&hl=en&gl=us&q=One+Battle+After+Another&si=AMgyJEtL6yuqx8LGDGAaloaQG1F-3HWSJLJFV8FPG1mfzVpr7rKpOMdeVIgxcKzR76mlk6ESRsJ2WpyruKyCNzTPgh0wgYAULmxqwwe5wPnBiNRN_SZAHFVKUki_M-0RAqSzLl_WteEKhiweIooNPhKC-YhsePM01XBtJ2W4JlByW4pnNQso6cY%3D",
                "showing": [
                    {
                        "time": [
                            "11:00am",
                            "12:45pm",
                            "2:30pm",
                            "4:30pm",
                            "6:15pm",
                            "7:45pm",
                            "9:00pm"
                        ],
                        "type": "Standard"
                    },
                    {
                        "time": [
                            "10:00pm"
                        ],
                        "type": "IMAX"
                    }
                ]
            },
            {
                "name": "Gabby's Dollhouse: The Movie",
                "link": "https://www.google.com/search?sca_esv=44ad9363d71d6b60&hl=en&gl=us&q=Gabby%27s+Dollhouse:+The+Movie&si=AMgyJEtL6yuqx8LGDGAaloaQG1F-3HWSJLJFV8FPG1mfzVpr7uhBKGbsq97cz0hk0CXuHjfR3gRcVq9-A_mGRbXqJTGop8SVgJOBnC_3CQFyHn3-k6FeJ8QLywEINlm9kECCnP7o_JI2suBrYQm4kiNeRm7pelxM1wv0ddrl87HAgGWopieneSE%3D",
                "showing": [
                    {
                        "time": [
                            "11:15am",
                            "1:15pm",
                            "4:00pm",
                            "6:45pm"
                        ],
                        "type": "Standard"
                    }
                ]
            },
            {
                "name": "The Strangers \u2013 Chapter 2",
                "link": "https://www.google.com/search?sca_esv=44ad9363d71d6b60&hl=en&gl=us&q=The+Strangers+%E2%80%93+Chapter+2&si=AMgyJEtL6yuqx8LGDGAaloaQG1F-3HWSJLJFV8FPG1mfzVpr7kv0FdpXmv_GKn1En9iAGCmmHDC0zYNNgQGZZELUn4zJcHfOxjVYcszcMZzZLUOeDkL3XrblWWRSo1hJCS1LFroEUiRBhDBLTrVAc28SzVkWoK1JKMWMFOdnzKVOF3jrcFQZGSU%3D",
                "showing": [
                    {
                        "time": [
                            "11:30am",
                            "2:15pm",
                            "5:00pm",
                            "8:15pm",
                            "11:00pm"
                        ],
                        "type": "Standard"
                    }
                ]
            },
            {
                "name": "The Conjuring: Last Rites",
                "link": "https://www.google.com/search?sca_esv=44ad9363d71d6b60&hl=en&gl=us&q=The+Conjuring:+Last+Rites&si=AMgyJEtL6yuqx8LGDGAaloaQG1F-3HWSJLJFV8FPG1mfzVpr7uLtZyVurtHgm0PFWEPcAKtTNKpZUsGMh5LfkwdBHH89QcYRYl-JnQTH4cuPVJHNzX0ym21dd5V7QVBMsqcHLb4wSD9e--tqL5z4nncIKJumdGFc0-y1LvrXcxE0fYR1z9pcssM%3D",
                "showing": [
                    {
                        "time": [
                            "12:30pm",
                            "3:45pm",
                            "8:30pm",
                            "10:00pm"
                        ],
                        "type": "Standard"
                    }
                ]
            },
            {
                "name": "Demon Slayer: Kimetsu No Yaiba The Movie: Infinity Castle",
                "link": "https://www.google.com/search?sca_esv=44ad9363d71d6b60&hl=en&gl=us&q=Demon+Slayer:+Kimetsu+No+Yaiba+The+Movie:+Infinity+Castle&si=AMgyJEtL6yuqx8LGDGAaloaQG1F-3HWSJLJFV8FPG1mfzVpr7kDjG2IS--41swzef_MpaMiBczpZWaT0xadENqJHhkJJXe5ahFpuIry1kBvqsJo0lphhKiYqXD7UdFA3k16jAZstbKDbXqR6QUncn2luA8xGceSnJWTYxgYFhhuLwLggQBfVegw%3D",
                "showing": [
                    {
                        "time": [
                            "3:45pm",
                            "9:30pm"
                        ],
                        "type": "Standard"
                    },
                    {
                        "time": [
                            "12:15pm",
                            "7:15pm"
                        ],
                        "type": "Standard"
                    }
                ]
            },
            {
                "name": "Avatar: The Way of Water Re-Release 3D",
                "link": "https://www.google.com/search?sca_esv=44ad9363d71d6b60&hl=en&gl=us&q=Avatar:+The+Way+of+Water+Re-Release+3D&si=AMgyJEtL6yuqx8LGDGAaloaQG1F-3HWSJLJFV8FPG1mfzVpr7gmzW5qv5okuqfMDm47oXEmV0MGUWh-sxqZrUMBdVGWvSvKGEM5XtU1vs8Q9S4hmwEyLB5trIwNedUa_430ikcmE4OAuQBu_2J4OoOVBISZXgBHhPtdAp73yEn41-Rb1493GWBI%3D",
                "showing": [
                    {
                        "time": [
                            "2:45pm"
                        ],
                        "type": "IMAX 3D"
                    },
                    {
                        "time": [
                            "2:15pm",
                            "6:30pm"
                        ],
                        "type": "3D"
                    }
                ]
            },
            {
                "name": "The Long Walk",
                "link": "https://www.google.com/search?sca_esv=44ad9363d71d6b60&hl=en&gl=us&q=The+Long+Walk&si=AMgyJEtL6yuqx8LGDGAaloaQG1F-3HWSJLJFV8FPG1mfzVpr7r-4V46gmTlu4_dzI96ROD5714y21laa13MFiUoRfSXnyNTZKl6uykWCZJxWKu-yPC0Bbl_K4NXEhFe2Vd0tZhRIGmSc6ZkGLHAAVLSF25BVAcPR4NNOxqb2pY3eaZ-kD9nymiU%3D",
                "showing": [
                    {
                        "time": [
                            "5:00pm",
                            "8:00pm",
                            "10:45pm"
                        ],
                        "type": "Standard"
                    }
                ]
            },
            {
                "name": "Good Boy",
                "link": "https://www.google.com/search?sca_esv=44ad9363d71d6b60&hl=en&gl=us&q=Good+Boy&si=AMgyJEtL6yuqx8LGDGAaloaQG1F-3HWSJLJFV8FPG1mfzVpr7rt-pH93pC0MCSpAdNKloM9FIOaf6zcxL3lk2ePUkS74Jn37KgsQ0rfXLowf6yISldTRA0J5dWyN2CMzEf9Tw68e_Uc7LLtqDucoSnNaSSxmbMwN1hbTqVJyQYAjZcxbWBpXXto%3D",
                "showing": [
                    {
                        "time": [
                            "11:00am",
                            "12:45pm",
                            "3:00pm",
                            "5:15pm",
                            "7:30pm",
                            "8:30pm",
                            "9:45pm",
                            "10:45pm"
                        ],
                        "type": "Standard"
                    }
                ]
            },
            {
                "name": "Downton Abbey: The Grand Finale",
                "link": "https://www.google.com/search?sca_esv=44ad9363d71d6b60&hl=en&gl=us&q=Downton+Abbey:+The+Grand+Finale&si=AMgyJEtL6yuqx8LGDGAaloaQG1F-3HWSJLJFV8FPG1mfzVpr7hTGgaq6AP_6TkuZX5Pf2f1Xb8qBOAGvTGUEodCcYyEZbiWrNkpuU4eLGYLw8oR_OfdCFBhC5NBlww4OtqWncLJvblWJXG_QIoyjDzIq_YhxOq_z-AnA3W7un9K9uXC6mzKXbz0%3D",
                "showing": [
                    {
                        "time": [
                            "12:00pm"
                        ],
                        "type": "Standard"
                    }
                ]
            },
            {
                "name": "Him",
                "link": "https://www.google.com/search?sca_esv=44ad9363d71d6b60&hl=en&gl=us&q=Him&si=AMgyJEtL6yuqx8LGDGAaloaQG1F-3HWSJLJFV8FPG1mfzVpr7mTYznzzSMIVBbUEDLGMxKmii1W-v9nsnG-24kplPq9pwgQ-1O1FA3Ci7H2fBln5evBK9kxjh9dYerde2a3_RZkFedEQs1r4BJvksfGMDzP-sRt1rO9BBrlSx2U-QUAQIkSqecQ%3D",
                "showing": [
                    {
                        "time": [
                            "12:00pm",
                            "5:45pm"
                        ],
                        "type": "Standard"
                    }
                ]
            },
            {
                "name": "Anemone",
                "link": "https://www.google.com/search?sca_esv=44ad9363d71d6b60&hl=en&gl=us&q=Anemone&si=AMgyJEtL6yuqx8LGDGAaloaQG1F-3HWSJLJFV8FPG1mfzVpr7s2uDltDIW1XlRefV3C3PCsxmiKUj5otmLQcaaOV5SMPfN8yEBVvaAH-ViJeGWX2HY55AU39wg2eUkUTJoi10dzR3ys4FDcc4HUyeuAcdHhTUma_fbtNr4DlZrcn9ORqcNd0P-c%3D",
                "showing": [
                    {
                        "time": [
                            "1:00pm",
                            "4:00pm",
                            "7:00pm",
                            "10:00pm"
                        ],
                        "type": "Standard"
                    }
                ]
            },
            {
                "name": "Bone Lake",
                "link": "https://www.google.com/search?sca_esv=44ad9363d71d6b60&hl=en&gl=us&q=Bone+Lake&si=AMgyJEtL6yuqx8LGDGAaloaQG1F-3HWSJLJFV8FPG1mfzVpr7gBai5At1MRuG3dTPhls8E1O9mP86kEQQA_fELMJL9sGSXD7USLmrj0tzofW6tGQs6TNh5hD5qXHx4rEd9rqHxhU6GywC7k3DHFW0lvrxSEop47ljlYeEJamwqfQLpiwb-N7gKE%3D",
                "showing": [
                    {
                        "time": [
                            "12:00pm",
                            "2:30pm",
                            "5:00pm",
                            "7:30pm",
                            "10:00pm",
                            "11:00pm"
                        ],
                        "type": "Standard"
                    }
                ]
            },
            {
                "name": "Casper: 30th Anniversary",
                "link": "https://www.google.com/search?sca_esv=44ad9363d71d6b60&hl=en&gl=us&q=Casper:+30th+Anniversary&si=AMgyJEtL6yuqx8LGDGAaloaQG1F-3HWSJLJFV8FPG1mfzVpr7szPlFI0dAAyHaLSICDt-9XKkxi0iqc4uL_MaHv8y155xN1_bQ7A5tU-2AdUnkJASaNWtJWpQwvSd5a4MyYS4-QGsgCyEe67udUdGBMauzP2_6g1fU3wKVtpErp16ubAiTP7p8I%3D",
                "showing": [
                    {
                        "time": [
                            "3:45pm",
                            "6:30pm"
                        ],
                        "type": "Standard"
                    }
                ]
            },
            {
                "name": "Kantara A Legend: Chapter 1",
                "link": "https://www.google.com/search?sca_esv=44ad9363d71d6b60&hl=en&gl=us&q=Kantara+A+Legend:+Chapter+1&si=AMgyJEtDcoZTubXsRk8TZioN0aq7DlbGMYlPSjPPUZB8zAtUmv9SYBQK4Y25uFn3GHv9mhax4CI6-8_nl_8f60o2ujmun5mAeYh_9PGGoGAhvZ2NPFAFCw_e5Hax4zmasL45GCRo_Rny9vFKLErqofDO2InXYNGwJpNg5oFZ0cqJzPB15Y5lYt-EFbnfT_f7QAI0ST3tia0G_VTzxybsezxuavYpDaugB-E0gzoYgQVpX18K8vEf7Rg%3D",
                "showing": [
                    {
                        "time": [
                            "3:15pm",
                            "5:15pm",
                            "9:00pm"
                        ],
                        "type": "Standard"
                    }
                ]
            },
            {
                "name": "Perfect Blue Remastered",
                "link": "https://www.google.com/search?sca_esv=44ad9363d71d6b60&hl=en&gl=us&q=Perfect+Blue+Remastered&si=AMgyJEtDcoZTubXsRk8TZioN0aq7DlbGMYlPSjPPUZB8zAtUmv9SYBQK4Y25uFn3GHv9mhaGSO-rJYp8KJWuG4zNhTgupUy371O7t3NrLZXaDA7rVb8r_3DoA5m4pJZS5y7jcC71FFKvuYug9BnUOL1WWaNmDTgegcbCnYLTEGiIJI3j_IWVXclCA5nvMwFTQjPj6nOzIV0_iK0jT-9WEzRxJRLzZkmQaAhMuhtX6pGtd9X7UJukfCw%3D",
                "showing": [
                    {
                        "time": [
                            "11:00am",
                            "1:30pm",
                            "4:00pm",
                            "6:30pm",
                            "11:00pm"
                        ],
                        "type": "Standard"
                    }
                ]
            },
            {
                "name": "Eleanor the Great",
                "link": "https://www.google.com/search?sca_esv=44ad9363d71d6b60&hl=en&gl=us&q=Eleanor+the+Great&si=AMgyJEtL6yuqx8LGDGAaloaQG1F-3HWSJLJFV8FPG1mfzVpr7hBAQsFwG_ccq3aSQsof1jws5R0dca7IL2Cl8QFyfDCagrdVdF0lMh2nDwva9CMeEfdF1povGZ3L2zHB4hQsJv0ha3G70nVDFoXLM1F8Ew5cIiCgzkLqKZXkRwQ-4nDh9XZx_38%3D",
                "showing": [
                    {
                        "time": [
                            "1:00pm",
                            "9:15pm"
                        ],
                        "type": "Standard"
                    }
                ]
            },
            {
                "name": "A Big Bold Beautiful Journey",
                "link": "https://www.google.com/search?sca_esv=44ad9363d71d6b60&hl=en&gl=us&q=A+Big+Bold+Beautiful+Journey&si=AMgyJEtL6yuqx8LGDGAaloaQG1F-3HWSJLJFV8FPG1mfzVpr7lh_OJeIF5VP2j0JGt-sG18bL79zEEl1DQVn_XPAFmnV7L6Omkn-StRpJXOO69qtZpMTep-n8eom8AbD5GWT5lXDu-4vkYS7rcCFQjubjM6SAD-l8McSPWX_B47vXkWqogm6t34%3D",
                "showing": [
                    {
                        "time": [
                            "3:00pm"
                        ],
                        "type": "Standard"
                    }
                ]
            },
            {
                "name": "Dead of Winter",
                "link": "https://www.google.com/search?sca_esv=44ad9363d71d6b60&hl=en&gl=us&q=Dead+of+Winter&si=AMgyJEtL6yuqx8LGDGAaloaQG1F-3HWSJLJFV8FPG1mfzVpr7nqHv1tt0Zz8npbHwoHQqX68J_oCd1dJY7eXZuU9SeAPy01gVWlECANMHmVp3CyrzVHIJthjgvpGu_4Zu_bFOLshbXtpaUXlsEwWtzV7tbiyy0wnI9UBN4RI5MvujiUeoQ6c20w%3D",
                "showing": [
                    {
                        "time": [
                            "1:45pm",
                            "5:45pm"
                        ],
                        "type": "Standard"
                    }
                ]
            },
            {
                "name": "Coyotes",
                "link": "https://www.google.com/search?sca_esv=44ad9363d71d6b60&hl=en&gl=us&q=Coyotes&si=AMgyJEtDcoZTubXsRk8TZioN0aq7DlbGMYlPSjPPUZB8zAtUmv9SYBQK4Y25uFn3GHv9mhbYm-Fh2PSB6Zz_UHnFnv4XqAakhosaAvn61Mi2HagUR_oHgBRT0WO6MD4hy4lcz_-hC5cB-hI7qXxBYwR-yTfj0SLi7IzNsoMXjvbRlQAfGkO9mcBf0kGpKrMdsIbB3s0KopivFu9t7O0OUUf07Nh6dMFi1A%3D%3D",
                "showing": [
                    {
                        "time": [
                            "9:30pm"
                        ],
                        "type": "Standard"
                    }
                ]
            },
            {
                "name": "The Devil's Rejects 20th Anniversary",
                "link": "https://www.google.com/search?sca_esv=44ad9363d71d6b60&hl=en&gl=us&q=The+Devil%27s+Rejects+20th+Anniversary&si=AMgyJEtDcoZTubXsRk8TZioN0aq7DlbGMYlPSjPPUZB8zAtUmv9SYBQK4Y25uFn3GHv9mhZ4uO3A-r0BTBYxzWRunGUWcVgvOjx_X4ITaRusrwHF71Nz8ZaWsJ0G8QkBhV7rFXbwSqOEm7SkYiltOxmuvWHJowjO7v8mT1-2pmt05x-dwtX-JQM590dTg6vZZGPXOiZ089ta4-iKCkBoy-nEJcyj5VZ3mWhR1Lz6Sn2EgGbjmBpln_l-XwhKzsq9yeABEvZPgeCz",
                "showing": [
                    {
                        "time": [
                            "7:00pm"
                        ],
                        "type": "Standard"
                    }
                ]
            },
            {
                "name": "They Call Him OG",
                "link": "https://www.google.com/search?sca_esv=44ad9363d71d6b60&hl=en&gl=us&q=They+Call+Him+OG&si=AMgyJEtDcoZTubXsRk8TZioN0aq7DlbGMYlPSjPPUZB8zAtUmv9SYBQK4Y25uFn3GHv9mhaphcEOhY7AGtDO3Dd9ENfWihu-H2S4xFTGS_ydR0HVeLEcyR6oaklNGme56uwtMNjX9Pr9JNp9MzrwZTdTPyiJB-ZgCfj7PVnwLFmOZKbExjh5dj8UOL7S9YF4230DAqECw-UkhpDM1JhU_S4ZnBvAGF4cBzCi-a6zSMYapwiphvM2QJU%3D",
                "showing": [
                    {
                        "time": [
                            "12:45pm"
                        ],
                        "type": "Standard"
                    }
                ]
            },
            {
                "name": "Sunny Sanskari Ki Tulsi Kumari",
                "link": "https://www.google.com/search?sca_esv=44ad9363d71d6b60&hl=en&gl=us&q=Sunny+Sanskari+Ki+Tulsi+Kumari&si=AMgyJEtDcoZTubXsRk8TZioN0aq7DlbGMYlPSjPPUZB8zAtUmv9SYBQK4Y25uFn3GHv9mhY0MZZLrTjqjlSarKfYDlqPDyVQvGPWIOSIz4EAiV2QDIdedbi1ZkxZAilgluI2da_H5vdfRyYYkC4bRo5tsz-AB-swYrd_NpX0Vk3VhOKuIFJQ0XbKcFGQb6JPDucHo3_OSRGzBcgzoexVZWhXAfP2WAEM53afrn86iDQRVUBYFXJF5cyX447hQYewA_rI4UcgDAo9",
                "showing": [
                    {
                        "time": [
                            "11:45am",
                            "2:45pm"
                        ],
                        "type": "Standard"
                    }
                ]
            },
            {
                "name": "Killing Faith",
                "link": "https://www.google.com/search?sca_esv=44ad9363d71d6b60&hl=en&gl=us&q=Killing+Faith&si=AMgyJEtDcoZTubXsRk8TZioN0aq7DlbGMYlPSjPPUZB8zAtUmv9SYBQK4Y25uFn3GHv9mhYHk9O5EAUArP5HNqB3_SymfdLfg_wGIL2DV131kBljEPx6vsqQ6k8vC2Bj3HX5yYK7e8zVFuZvqZxyLLRyhvq0TnQz3Rg-3IRv-udFoWzU_h6BX08HFKRNbOSu7_v3s1Uouwh9gAvxFIpoPy7XBZEMyjl3eA%3D%3D",
                "showing": [
                    {
                        "time": [
                            "1:15pm",
                            "9:45pm"
                        ],
                        "type": "Standard"
                    }
                ]
            },
            {
                "name": "Are We Good?",
                "link": "https://www.google.com/search?sca_esv=44ad9363d71d6b60&hl=en&gl=us&q=Are+We+Good%3F&si=AMgyJEtDcoZTubXsRk8TZioN0aq7DlbGMYlPSjPPUZB8zAtUmv9SYBQK4Y25uFn3GHv9mhaH7xff6szHJLRPoeJtRCCSDuV-KIx92kCCFV9z44NJHdZV4JkspZy6rTpa1ZLFYQGdzN2JDLvYp2rKjWvCnbXQ9W3gYLgKg-wG22B_REx0-ICDhFZ2Bv4MnXxds7zeaBiTluLnY7rp2iyDsTGGpa8uVi1U2A%3D%3D",
                "showing": [
                    {
                        "time": [
                            "11:00am",
                            "1:40pm",
                            "4:15pm",
                            "7:00pm"
                        ],
                        "type": "Standard"
                    }
                ]
            },
            {
                "name": "Afterburn",
                "link": "https://www.google.com/search?sca_esv=44ad9363d71d6b60&hl=en&gl=us&q=Afterburn&si=AMgyJEtDcoZTubXsRk8TZioN0aq7DlbGMYlPSjPPUZB8zAtUmv9SYBQK4Y25uFn3GHv9mhY3a9wU0JzeuGoochlCd9WtbKyAcZaoc1H4EmBKcL0p_jtccSOgVGjyDTQWwlkNmgFfabJmEDj_mxgV4cZlRTaF_N1EsfosNWgmXLA0PpjtzN_R_gH6QNQ3YLihSJgopeBGk13YjMRco5QKmUm1CdZgDZwnCA%3D%3D",
                "showing": [
                    {
                        "time": [
                            "4:15pm",
                            "9:45pm"
                        ],
                        "type": "Standard"
                    }
                ]
            },
            {
                "name": "A Writer's Odyssey 2",
                "link": "https://www.google.com/search?sca_esv=44ad9363d71d6b60&hl=en&gl=us&q=A+Writer%27s+Odyssey+2&si=AMgyJEtDcoZTubXsRk8TZioN0aq7DlbGMYlPSjPPUZB8zAtUmv9SYBQK4Y25uFn3GHv9mhbgUV4Lgtg8aV8DdvYkez4Y8YT43Arm6SdthO9YInesJTBQcyzHJweBvXLvXdoG8WwMIUTXszE9diEUCImwW8jN8GlWKoLKfnREG2TogjhJogP1RrEmgkqY7-vpKNitSBUmmxILCveNUk50HTebgJ-YgatHg7NpVs-bzfBFQ1_pt6WRXnM%3D",
                "showing": [
                    {
                        "time": [
                            "4:00pm",
                            "9:30pm"
                        ],
                        "type": "Standard"
                    }
                ]
            },
            {
                "name": "The Road Between Us: The Ultimate Rescue",
                "link": "https://www.google.com/search?sca_esv=44ad9363d71d6b60&hl=en&gl=us&q=The+Road+Between+Us:+The+Ultimate+Rescue&si=AMgyJEtDcoZTubXsRk8TZioN0aq7DlbGMYlPSjPPUZB8zAtUmv9SYBQK4Y25uFn3GHv9mhZ62iC4QzUfzdPQw3Nbmp69j_YzDP8TqaIY9yfz3fPZ0kxAllh0m9SjONu-wqKIGQIw-eQFeunrEc9_iOHpCISkslHive2S1wANskUiseYrWdzbnTN_a-bAf7Cf2qLwzVzSiTFAu66x56ufjGoYThsKr24Pc6Pf3nCTxceensFhH7aIUqLHbHRB60cbfHE-DbTf0kx8",
                "showing": [
                    {
                        "time": [
                            "11:45am",
                            "2:15pm"
                        ],
                        "type": "Standard"
                    }
                ]
            },
            {
                "name": "Friday the 13th",
                "link": "https://www.google.com/search?sca_esv=44ad9363d71d6b60&hl=en&gl=us&q=Friday+the+13th&si=AMgyJEtOM6syuX6VRum6KaFPd5B_TwdCG7coSz3KXwLvoU6WUYFzLF7b8ey6YDJlIGkpIV057O5z0B1SWRt32GSpr0IUl8BTqa4KC3ODgCc5n4isIFH1e9W2S5Z3wjVfRaMGCXxXvd6Ayz_LUvAkVNYDPN4dFCjNgb9w_Rg5dsWzvPDMlGKfnXA%3D",
                "showing": [
                    {
                        "time": [
                            "7:00pm",
                            "7:45pm",
                            "10:15pm"
                        ],
                        "type": "Standard"
                    }
                ]
            },
            {
                "name": "One Big Happy Family",
                "link": "https://www.google.com/search?sca_esv=44ad9363d71d6b60&hl=en&gl=us&q=One+Big+Happy+Family&si=AMgyJEtL6yuqx8LGDGAaloaQG1F-3HWSJLJFV8FPG1mfzVpr7vjN_XhqnI3L6X84IIs88TJ3yl97dd487AsKz8VvgQ4cRdKaWesCAQ73BrfqkvkDB2NY4qdAFhAjYSs7UP2vLJWdN603Ao___mhQqpeBnEf6aTYu5UwLttQ41FCRPZ2DPxiBe3Q%3D",
                "showing": [
                    {
                        "time": [
                            "11:15am",
                            "4:30pm",
                            "7:15pm"
                        ],
                        "type": "Standard"
                    }
                ]
            },
            {
                "name": "Nikka Zaildar 4",
                "link": "https://www.google.com/search?sca_esv=44ad9363d71d6b60&hl=en&gl=us&q=Nikka+Zaildar+4&si=AMgyJEtDcoZTubXsRk8TZioN0aq7DlbGMYlPSjPPUZB8zAtUmv9SYBQK4Y25uFn3GHv9mhaRxrECF8I_phKRnn0syMRNSQKuyU8oFkNjbcI-QA16NEgnRKY-i-oAP-S63MWK51kq30uiPIVESnjH5yaCBKeaGLlUdijCpDusfNTGc7YPlNGTG0zVBN9D_10z2-z5873_D2LLHsTkx1SuR8eQvEo2RwRG8LePbBJGb9O2PPWCOnkLJOY%3D",
                "showing": [
                    {
                        "time": [
                            "2:00pm"
                        ],
                        "type": "Standard"
                    }
                ]
            },
            {
                "name": "Tron: Ares Early Access Screening 3D",
                "link": "https://www.google.com/search?sca_esv=44ad9363d71d6b60&hl=en&gl=us&q=Tron:+Ares+Early+Access+Screening+3D&si=AMgyJEtDcoZTubXsRk8TZioN0aq7DlbGMYlPSjPPUZB8zAtUmv9SYBQK4Y25uFn3GHv9mhYW1O5tTmeXCT7__4lOprqZPjOtxSUpgNCu4Yn9xXFN9kgBY3d0ztavggyzkp3z16Kkv4qVbaBF0wJCtJCSRHkJhIQ2u5dlR_m3q4zMtXLLQ719L4jY1gMbw7kmInjqpzSv1GNhtG7kGb4eIblGk2oN4GMH4Fx5OZmvOn25CZGxVcOzdUjr2aCIaHpECSfIZFHIYpZw",
                "showing": [
                    {
                        "time": [
                            "7:00pm"
                        ],
                        "type": "IMAX 3D"
                    }
                ]
            },
            {
                "name": "Are We Good? Q&A with Marc Maron & Director Steven Feinartz",
                "link": "https://www.google.com/search?sca_esv=44ad9363d71d6b60&hl=en&gl=us&q=Are+We+Good%3F+Q%26A+with+Marc+Maron+%26+Director+Steven+Feinartz&si=AMgyJEtDcoZTubXsRk8TZioN0aq7DlbGMYlPSjPPUZB8zAtUmv9SYBQK4Y25uFn3GHv9mhaBs0eGuk1YAbysi0iJej_k5yuslEzau25ha1VeWOKOtX-mHJ5ZXan5X46X2CsN_Oq8yWouRMqOPmESeFu62odekQpACw0V0FSqSOP3kSo6zJY61WHblToV6MGMG5yMcTYg5EDkyTnMvKqiJqmBwFKZiy6d9J8wGoTsn5fcAVJSlPKRSvILeJwyN8gYaDji81C27Fa9Qs92fGK1eAuOxKajSl1gGQ%3D%3D",
                "showing": [
                    {
                        "time": [
                            "7:30pm"
                        ],
                        "type": "Standard"
                    }
                ]
            }
        ]
    },
    {
        "day": "Thu",
        "date": "Oct 9",
        "movies": [
            {
                "name": "Tron: Ares",
                "link": "https://www.google.com/search?sca_esv=44ad9363d71d6b60&hl=en&gl=us&q=Tron:+Ares&si=AMgyJEtL6yuqx8LGDGAaloaQG1F-3HWSJLJFV8FPG1mfzVpr7uOHaHrSTZBWu79HPytpOCqnCJpdR7wuCka0Kz9PUcsNON2VtACHnURzbPVsYDUtGGDkjp6q57GJflpjqGjHb12j8tTG_FqeqUXzBNUN_dtJ6Qm4iTu47wWZhliJR5f8mcEApx0%3D",
                "showing": [
                    {
                        "time": [
                            "3:00pm",
                            "6:00pm",
                            "9:00pm",
                            "10:30pm"
                        ],
                        "type": "Standard"
                    },
                    {
                        "time": [
                            "5:00pm",
                            "8:00pm"
                        ],
                        "type": "IMAX"
                    },
                    {
                        "time": [
                            "2:00pm",
                            "11:00pm"
                        ],
                        "type": "IMAX 3D"
                    },
                    {
                        "time": [
                            "4:00pm",
                            "4:30pm",
                            "5:30pm",
                            "7:00pm",
                            "7:30pm",
                            "8:30pm",
                            "10:00pm"
                        ],
                        "type": "3D"
                    },
                    {
                        "time": [
                            "2:30pm",
                            "11:30pm"
                        ],
                        "type": "Dolby Cinema"
                    }
                ]
            },
            {
                "name": "Roofman",
                "link": "https://www.google.com/search?sca_esv=44ad9363d71d6b60&hl=en&gl=us&q=Roofman&si=AMgyJEtL6yuqx8LGDGAaloaQG1F-3HWSJLJFV8FPG1mfzVpr7t1aUcsyQBWSLlCmXKb-mYeH_e4LeJV7Nj2w1oZbceF_sQeX7ywe4HbeL7t7risgFRcm8Qzo0zC7mKGbGTE3TAcxR2zFOjTqgy5toieE9RLc1cpEqDM0RM25hUOOSQ-BbJTG_Rw%3D",
                "showing": [
                    {
                        "time": [
                            "7:00pm",
                            "10:15pm"
                        ],
                        "type": "Standard"
                    }
                ]
            },
            {
                "name": "The Smashing Machine",
                "link": "https://www.google.com/search?sca_esv=44ad9363d71d6b60&hl=en&gl=us&q=The+Smashing+Machine&si=AMgyJEtL6yuqx8LGDGAaloaQG1F-3HWSJLJFV8FPG1mfzVpr7pFTpX3dehRqIOn6u0JOXDVtudT-mIStenAOLOihbtG_7gPsXZDgTk1NKMJ7FZdG36NAPIqVn4eQsjyRcs4x-TVhnAdlHpHj_-JPTfANQYweFBVv9OWrDgHD72I47Zhq0A5Ywpo%3D",
                "showing": [
                    {
                        "time": [
                            "12:45pm",
                            "3:45pm",
                            "6:45pm"
                        ],
                        "type": "Standard"
                    }
                ]
            },
            {
                "name": "One Battle After Another",
                "link": "https://www.google.com/search?sca_esv=44ad9363d71d6b60&hl=en&gl=us&q=One+Battle+After+Another&si=AMgyJEtL6yuqx8LGDGAaloaQG1F-3HWSJLJFV8FPG1mfzVpr7rKpOMdeVIgxcKzR76mlk6ESRsJ2WpyruKyCNzTPgh0wgYAULmxqwwe5wPnBiNRN_SZAHFVKUki_M-0RAqSzLl_WteEKhiweIooNPhKC-YhsePM01XBtJ2W4JlByW4pnNQso6cY%3D",
                "showing": [
                    {
                        "time": [
                            "12:45pm",
                            "4:30pm",
                            "7:45pm",
                            "9:00pm"
                        ],
                        "type": "Standard"
                    }
                ]
            },
            {
                "name": "The Strangers \u2013 Chapter 2",
                "link": "https://www.google.com/search?sca_esv=44ad9363d71d6b60&hl=en&gl=us&q=The+Strangers+%E2%80%93+Chapter+2&si=AMgyJEtL6yuqx8LGDGAaloaQG1F-3HWSJLJFV8FPG1mfzVpr7kv0FdpXmv_GKn1En9iAGCmmHDC0zYNNgQGZZELUn4zJcHfOxjVYcszcMZzZLUOeDkL3XrblWWRSo1hJCS1LFroEUiRBhDBLTrVAc28SzVkWoK1JKMWMFOdnzKVOF3jrcFQZGSU%3D",
                "showing": [
                    {
                        "time": [
                            "11:30am",
                            "2:15pm",
                            "5:00pm",
                            "8:15pm",
                            "11:00pm"
                        ],
                        "type": "Standard"
                    }
                ]
            },
            {
                "name": "Soul on Fire",
                "link": "https://www.google.com/search?sca_esv=44ad9363d71d6b60&hl=en&gl=us&q=Soul+on+Fire&si=AMgyJEtL6yuqx8LGDGAaloaQG1F-3HWSJLJFV8FPG1mfzVpr7mWToINJReFU2IK8fy_2ypIJcWpXf4gCwSDeY8FB18G3L9fgNwSFIP4i2Qk6yJ6ZPhGZ605pgcfO-c8PR3ht84rsjW-OKZ61Ibg4zbNveG9fBxc6T0FGmGCMCF7YL8wGJ_ZJqDs%3D",
                "showing": [
                    {
                        "time": [
                            "4:00pm",
                            "7:00pm"
                        ],
                        "type": "Standard"
                    }
                ]
            },
            {
                "name": "Kiss of the Spider Woman",
                "link": "https://www.google.com/search?sca_esv=44ad9363d71d6b60&hl=en&gl=us&q=Kiss+of+the+Spider+Woman&si=AMgyJEtL6yuqx8LGDGAaloaQG1F-3HWSJLJFV8FPG1mfzVpr7u0Iel8TR-Kg7oSlWmvUjUOX-PQqp04sC0fsP8ShrNnZaQ0kuEWuqpbp-2OdAnvXsfy8g-UqdKkFh3RkUAnv2rWXmv_X5t8085VWsqroGB4ksqA5O96ZmM-MP8xQD5tMvy8VFW8%3D",
                "showing": [
                    {
                        "time": [
                            "4:00pm",
                            "7:15pm",
                            "10:30pm"
                        ],
                        "type": "Standard"
                    }
                ]
            },
            {
                "name": "Casper: 30th Anniversary",
                "link": "https://www.google.com/search?sca_esv=44ad9363d71d6b60&hl=en&gl=us&q=Casper:+30th+Anniversary&si=AMgyJEtL6yuqx8LGDGAaloaQG1F-3HWSJLJFV8FPG1mfzVpr7szPlFI0dAAyHaLSICDt-9XKkxi0iqc4uL_MaHv8y155xN1_bQ7A5tU-2AdUnkJASaNWtJWpQwvSd5a4MyYS4-QGsgCyEe67udUdGBMauzP2_6g1fU3wKVtpErp16ubAiTP7p8I%3D",
                "showing": [
                    {
                        "time": [
                            "6:30pm"
                        ],
                        "type": "Standard"
                    }
                ]
            }
        ]
    },
    {
        "day": "Fri",
        "date": "Oct 10",
        "movies": [
            {
                "name": "Tron: Ares",
                "link": "https://www.google.com/search?sca_esv=44ad9363d71d6b60&hl=en&gl=us&q=Tron:+Ares&si=AMgyJEtL6yuqx8LGDGAaloaQG1F-3HWSJLJFV8FPG1mfzVpr7uOHaHrSTZBWu79HPytpOCqnCJpdR7wuCka0Kz9PUcsNON2VtACHnURzbPVsYDUtGGDkjp6q57GJflpjqGjHb12j8tTG_FqeqUXzBNUN_dtJ6Qm4iTu47wWZhliJR5f8mcEApx0%3D",
                "showing": [
                    {
                        "time": [
                            "10:30am",
                            "12:00pm",
                            "12:30pm",
                            "1:30pm",
                            "4:30pm",
                            "7:30pm",
                            "10:30pm"
                        ],
                        "type": "Standard"
                    },
                    {
                        "time": [
                            "10:00am",
                            "4:00pm",
                            "7:00pm"
                        ],
                        "type": "IMAX"
                    },
                    {
                        "time": [
                            "1:00pm",
                            "10:00pm"
                        ],
                        "type": "IMAX 3D"
                    },
                    {
                        "time": [
                            "3:00pm",
                            "3:30pm",
                            "5:00pm",
                            "6:00pm",
                            "6:30pm",
                            "8:00pm",
                            "9:00pm",
                            "9:30pm"
                        ],
                        "type": "3D"
                    },
                    {
                        "time": [
                            "11:00am",
                            "2:00pm",
                            "11:00pm"
                        ],
                        "type": "Dolby Cinema"
                    }
                ]
            },
            {
                "name": "Roofman",
                "link": "https://www.google.com/search?sca_esv=44ad9363d71d6b60&hl=en&gl=us&q=Roofman&si=AMgyJEtL6yuqx8LGDGAaloaQG1F-3HWSJLJFV8FPG1mfzVpr7t1aUcsyQBWSLlCmXKb-mYeH_e4LeJV7Nj2w1oZbceF_sQeX7ywe4HbeL7t7risgFRcm8Qzo0zC7mKGbGTE3TAcxR2zFOjTqgy5toieE9RLc1cpEqDM0RM25hUOOSQ-BbJTG_Rw%3D",
                "showing": [
                    {
                        "time": [
                            "10:00am",
                            "1:15pm",
                            "4:30pm",
                            "7:45pm",
                            "11:00pm"
                        ],
                        "type": "Standard"
                    }
                ]
            },
            {
                "name": "The Smashing Machine",
                "link": "https://www.google.com/search?sca_esv=44ad9363d71d6b60&hl=en&gl=us&q=The+Smashing+Machine&si=AMgyJEtL6yuqx8LGDGAaloaQG1F-3HWSJLJFV8FPG1mfzVpr7pFTpX3dehRqIOn6u0JOXDVtudT-mIStenAOLOihbtG_7gPsXZDgTk1NKMJ7FZdG36NAPIqVn4eQsjyRcs4x-TVhnAdlHpHj_-JPTfANQYweFBVv9OWrDgHD72I47Zhq0A5Ywpo%3D",
                "showing": [
                    {
                        "time": [
                            "4:30pm",
                            "7:30pm"
                        ],
                        "type": "Standard"
                    }
                ]
            },
            {
                "name": "Soul on Fire",
                "link": "https://www.google.com/search?sca_esv=44ad9363d71d6b60&hl=en&gl=us&q=Soul+on+Fire&si=AMgyJEtL6yuqx8LGDGAaloaQG1F-3HWSJLJFV8FPG1mfzVpr7mWToINJReFU2IK8fy_2ypIJcWpXf4gCwSDeY8FB18G3L9fgNwSFIP4i2Qk6yJ6ZPhGZ605pgcfO-c8PR3ht84rsjW-OKZ61Ibg4zbNveG9fBxc6T0FGmGCMCF7YL8wGJ_ZJqDs%3D",
                "showing": [
                    {
                        "time": [
                            "4:00pm",
                            "7:00pm"
                        ],
                        "type": "Standard"
                    }
                ]
            },
            {
                "name": "Kiss of the Spider Woman",
                "link": "https://www.google.com/search?sca_esv=44ad9363d71d6b60&hl=en&gl=us&q=Kiss+of+the+Spider+Woman&si=AMgyJEtL6yuqx8LGDGAaloaQG1F-3HWSJLJFV8FPG1mfzVpr7u0Iel8TR-Kg7oSlWmvUjUOX-PQqp04sC0fsP8ShrNnZaQ0kuEWuqpbp-2OdAnvXsfy8g-UqdKkFh3RkUAnv2rWXmv_X5t8085VWsqroGB4ksqA5O96ZmM-MP8xQD5tMvy8VFW8%3D",
                "showing": [
                    {
                        "time": [
                            "12:45pm",
                            "4:00pm",
                            "7:15pm",
                            "10:30pm"
                        ],
                        "type": "Standard"
                    }
                ]
            }
        ]
    },
    {
        "day": "Sat",
        "date": "Oct 11",
        "movies": [
            {
                "name": "Tron: Ares",
                "link": "https://www.google.com/search?sca_esv=44ad9363d71d6b60&hl=en&gl=us&q=Tron:+Ares&si=AMgyJEtL6yuqx8LGDGAaloaQG1F-3HWSJLJFV8FPG1mfzVpr7uOHaHrSTZBWu79HPytpOCqnCJpdR7wuCka0Kz9PUcsNON2VtACHnURzbPVsYDUtGGDkjp6q57GJflpjqGjHb12j8tTG_FqeqUXzBNUN_dtJ6Qm4iTu47wWZhliJR5f8mcEApx0%3D",
                "showing": [
                    {
                        "time": [
                            "10:30am",
                            "12:00pm",
                            "1:30pm",
                            "4:30pm",
                            "7:30pm",
                            "10:30pm",
                            "12:00am"
                        ],
                        "type": "Standard"
                    },
                    {
                        "time": [
                            "10:00am",
                            "4:00pm",
                            "7:00pm"
                        ],
                        "type": "IMAX"
                    },
                    {
                        "time": [
                            "1:00pm",
                            "10:00pm"
                        ],
                        "type": "IMAX 3D"
                    },
                    {
                        "time": [
                            "12:30pm",
                            "3:00pm",
                            "3:30pm",
                            "5:00pm",
                            "6:00pm",
                            "6:30pm",
                            "8:00pm",
                            "9:00pm",
                            "9:30pm"
                        ],
                        "type": "3D"
                    },
                    {
                        "time": [
                            "3:30pm"
                        ],
                        "type": "Standard"
                    },
                    {
                        "time": [
                            "11:00am",
                            "2:00pm",
                            "11:00pm"
                        ],
                        "type": "Dolby Cinema"
                    }
                ]
            },
            {
                "name": "Roofman",
                "link": "https://www.google.com/search?sca_esv=44ad9363d71d6b60&hl=en&gl=us&q=Roofman&si=AMgyJEtL6yuqx8LGDGAaloaQG1F-3HWSJLJFV8FPG1mfzVpr7t1aUcsyQBWSLlCmXKb-mYeH_e4LeJV7Nj2w1oZbceF_sQeX7ywe4HbeL7t7risgFRcm8Qzo0zC7mKGbGTE3TAcxR2zFOjTqgy5toieE9RLc1cpEqDM0RM25hUOOSQ-BbJTG_Rw%3D",
                "showing": [
                    {
                        "time": [
                            "10:00am",
                            "1:15pm",
                            "4:30pm",
                            "7:45pm",
                            "11:00pm"
                        ],
                        "type": "Standard"
                    }
                ]
            },
            {
                "name": "The Smashing Machine",
                "link": "https://www.google.com/search?sca_esv=44ad9363d71d6b60&hl=en&gl=us&q=The+Smashing+Machine&si=AMgyJEtL6yuqx8LGDGAaloaQG1F-3HWSJLJFV8FPG1mfzVpr7pFTpX3dehRqIOn6u0JOXDVtudT-mIStenAOLOihbtG_7gPsXZDgTk1NKMJ7FZdG36NAPIqVn4eQsjyRcs4x-TVhnAdlHpHj_-JPTfANQYweFBVv9OWrDgHD72I47Zhq0A5Ywpo%3D",
                "showing": [
                    {
                        "time": [
                            "4:30pm",
                            "7:30pm"
                        ],
                        "type": "Standard"
                    }
                ]
            },
            {
                "name": "Soul on Fire",
                "link": "https://www.google.com/search?sca_esv=44ad9363d71d6b60&hl=en&gl=us&q=Soul+on+Fire&si=AMgyJEtL6yuqx8LGDGAaloaQG1F-3HWSJLJFV8FPG1mfzVpr7mWToINJReFU2IK8fy_2ypIJcWpXf4gCwSDeY8FB18G3L9fgNwSFIP4i2Qk6yJ6ZPhGZ605pgcfO-c8PR3ht84rsjW-OKZ61Ibg4zbNveG9fBxc6T0FGmGCMCF7YL8wGJ_ZJqDs%3D",
                "showing": [
                    {
                        "time": [
                            "4:00pm",
                            "7:00pm"
                        ],
                        "type": "Standard"
                    }
                ]
            },
            {
                "name": "Kiss of the Spider Woman",
                "link": "https://www.google.com/search?sca_esv=44ad9363d71d6b60&hl=en&gl=us&q=Kiss+of+the+Spider+Woman&si=AMgyJEtL6yuqx8LGDGAaloaQG1F-3HWSJLJFV8FPG1mfzVpr7u0Iel8TR-Kg7oSlWmvUjUOX-PQqp04sC0fsP8ShrNnZaQ0kuEWuqpbp-2OdAnvXsfy8g-UqdKkFh3RkUAnv2rWXmv_X5t8085VWsqroGB4ksqA5O96ZmM-MP8xQD5tMvy8VFW8%3D",
                "showing": [
                    {
                        "time": [
                            "12:45pm",
                            "4:00pm",
                            "7:15pm",
                            "10:30pm"
                        ],
                        "type": "Standard"
                    }
                ]
            }
        ]
    },
    {
        "day": "Sun",
        "date": "Oct 12",
        "movies": [
            {
                "name": "Tron: Ares",
                "link": "https://www.google.com/search?sca_esv=44ad9363d71d6b60&hl=en&gl=us&q=Tron:+Ares&si=AMgyJEtL6yuqx8LGDGAaloaQG1F-3HWSJLJFV8FPG1mfzVpr7uOHaHrSTZBWu79HPytpOCqnCJpdR7wuCka0Kz9PUcsNON2VtACHnURzbPVsYDUtGGDkjp6q57GJflpjqGjHb12j8tTG_FqeqUXzBNUN_dtJ6Qm4iTu47wWZhliJR5f8mcEApx0%3D",
                "showing": [
                    {
                        "time": [
                            "10:30am",
                            "12:00pm",
                            "1:30pm",
                            "3:00pm",
                            "6:00pm",
                            "9:00pm",
                            "10:30pm",
                            "12:00am"
                        ],
                        "type": "Standard"
                    },
                    {
                        "time": [
                            "10:00am",
                            "4:00pm",
                            "7:00pm"
                        ],
                        "type": "IMAX"
                    },
                    {
                        "time": [
                            "1:00pm",
                            "10:00pm"
                        ],
                        "type": "IMAX 3D"
                    },
                    {
                        "time": [
                            "12:30pm",
                            "3:30pm",
                            "4:30pm",
                            "5:00pm",
                            "6:30pm",
                            "7:30pm",
                            "8:00pm",
                            "9:30pm"
                        ],
                        "type": "3D"
                    },
                    {
                        "time": [
                            "11:00am",
                            "2:00pm",
                            "11:00pm"
                        ],
                        "type": "Dolby Cinema"
                    }
                ]
            },
            {
                "name": "Roofman",
                "link": "https://www.google.com/search?sca_esv=44ad9363d71d6b60&hl=en&gl=us&q=Roofman&si=AMgyJEtL6yuqx8LGDGAaloaQG1F-3HWSJLJFV8FPG1mfzVpr7t1aUcsyQBWSLlCmXKb-mYeH_e4LeJV7Nj2w1oZbceF_sQeX7ywe4HbeL7t7risgFRcm8Qzo0zC7mKGbGTE3TAcxR2zFOjTqgy5toieE9RLc1cpEqDM0RM25hUOOSQ-BbJTG_Rw%3D",
                "showing": [
                    {
                        "time": [
                            "10:00am",
                            "1:15pm",
                            "4:30pm",
                            "7:45pm",
                            "11:00pm"
                        ],
                        "type": "Standard"
                    }
                ]
            },
            {
                "name": "The Smashing Machine",
                "link": "https://www.google.com/search?sca_esv=44ad9363d71d6b60&hl=en&gl=us&q=The+Smashing+Machine&si=AMgyJEtL6yuqx8LGDGAaloaQG1F-3HWSJLJFV8FPG1mfzVpr7pFTpX3dehRqIOn6u0JOXDVtudT-mIStenAOLOihbtG_7gPsXZDgTk1NKMJ7FZdG36NAPIqVn4eQsjyRcs4x-TVhnAdlHpHj_-JPTfANQYweFBVv9OWrDgHD72I47Zhq0A5Ywpo%3D",
                "showing": [
                    {
                        "time": [
                            "4:30pm",
                            "7:30pm"
                        ],
                        "type": "Standard"
                    }
                ]
            },
            {
                "name": "Soul on Fire",
                "link": "https://www.google.com/search?sca_esv=44ad9363d71d6b60&hl=en&gl=us&q=Soul+on+Fire&si=AMgyJEtL6yuqx8LGDGAaloaQG1F-3HWSJLJFV8FPG1mfzVpr7mWToINJReFU2IK8fy_2ypIJcWpXf4gCwSDeY8FB18G3L9fgNwSFIP4i2Qk6yJ6ZPhGZ605pgcfO-c8PR3ht84rsjW-OKZ61Ibg4zbNveG9fBxc6T0FGmGCMCF7YL8wGJ_ZJqDs%3D",
                "showing": [
                    {
                        "time": [
                            "4:00pm",
                            "7:00pm"
                        ],
                        "type": "Standard"
                    }
                ]
            },
            {
                "name": "Kiss of the Spider Woman",
                "link": "https://www.google.com/search?sca_esv=44ad9363d71d6b60&hl=en&gl=us&q=Kiss+of+the+Spider+Woman&si=AMgyJEtL6yuqx8LGDGAaloaQG1F-3HWSJLJFV8FPG1mfzVpr7u0Iel8TR-Kg7oSlWmvUjUOX-PQqp04sC0fsP8ShrNnZaQ0kuEWuqpbp-2OdAnvXsfy8g-UqdKkFh3RkUAnv2rWXmv_X5t8085VWsqroGB4ksqA5O96ZmM-MP8xQD5tMvy8VFW8%3D",
                "showing": [
                    {
                        "time": [
                            "12:45pm",
                            "4:00pm",
                            "7:15pm",
                            "10:30pm"
                        ],
                        "type": "Standard"
                    }
                ]
            },
            {
                "name": "The Dark Crystal",
                "link": "https://www.google.com/search?sca_esv=44ad9363d71d6b60&hl=en&gl=us&q=The+Dark+Crystal&si=AMgyJEtOM6syuX6VRum6KaFPd5B_TwdCG7coSz3KXwLvoU6WUfFbuIbdnABY8MimMuyctMB9sus69ozpIAb2_soIn780RycBBJscM1aegla8RxDRx3g4zhlkpLmmwydMwSqMVC9CTBfmqN0rSvEv9hz7uk1nJmZ2Y6WNZBcV_sWqMk5c6DIPiwU%3D",
                "showing": [
                    {
                        "time": [
                            "4:00pm",
                            "7:00pm"
                        ],
                        "type": "Standard"
                    }
                ]
            },
            {
                "name": "100 Meters",
                "link": "https://www.google.com/search?sca_esv=44ad9363d71d6b60&hl=en&gl=us&q=100+Meters&si=AMgyJEtDcoZTubXsRk8TZioN0aq7DlbGMYlPSjPPUZB8zAtUmv9SYBQK4Y25uFn3GHv9mhYNr96syCn-oF250s_2m268R17oavpnDeNVubkyXLaSqxFb1mxk2TaeqY0cy2WMk-wUzqMCjRfk2kuLGlawqyugbPfJVi9_qTD2JOezWaWhg_uk0IcacKksQ2pyGvYhtnk1jQG1ZtC07ZiITLcTh7EwuJ4CUQ%3D%3D",
                "showing": [
                    {
                        "time": [
                            "4:00pm"
                        ],
                        "type": "Standard"
                    }
                ]
            },
            {
                "name": "Battle Royale 25th Anniversary",
                "link": "https://www.google.com/search?sca_esv=44ad9363d71d6b60&hl=en&gl=us&q=Battle+Royale+25th+Anniversary&si=AMgyJEtDcoZTubXsRk8TZioN0aq7DlbGMYlPSjPPUZB8zAtUmv9SYBQK4Y25uFn3GHv9mhbfbEm6iOh40_xvL97n6POD7esawpKMqxjE8utALntwY9HwDdyCG11vbzaMP_xksKq2z8nmdnj2R__XOM1QuhioeuecHfRDkQqXj84UM1EHiObf5RbKWm0qORhMWNJiumwidmn-jgkxkYQw-lXxw0PO1_hbl_heLIuiP_Afr9E_rKfYZZdCuyP9TuQtHk_1g8OTPoaC",
                "showing": [
                    {
                        "time": [
                            "7:30pm"
                        ],
                        "type": "Standard"
                    }
                ]
            }
        ]
    }
]